Workbook

Sheet Executive Summary
A1: Babysteps v45 — Implemented Requirements Gap Audit
A4: Metric | B4: Value | D4: Audit basis | E4: Repository | F4: Branch | G4: HEAD | H4: Requirements | I4: Audit type | J4: Date
A5: Requirements audited | B5: 20 | D5: Static code-to-frozen-contract comparison | E5: SridharVoleti/babystepsindia | F5: master | G5: 517e3cf3ef141908679742ef2abb60dd93b32400 | H5: Babysteps_Platform_Requirements_v45.xlsx | I5: Behavior + architecture + integration gaps | J5: 2026-08-08
A6: Distinct gaps identified | B6: 107
A7: Critical gaps | B7: =COUNTIF('Gap Register'!$C$2:$C$500,"Critical") -> 11
A8: Requirements below 70% | B8: =COUNTIF('Requirement Match'!$H$2:$H$21,"<0.7") -> 5
A9: Weighted match | B9: =SUMPRODUCT('Requirement Match'!$C$2:$C$21,'Requirement Match'!$H$2:$H$21)/SUM('Requirement Match'!$C$2:$C$21) -> 0.74567723
A12: Requirement | B12: Title | C12: Match % | D12: Stage | E12: Confidence | F12: Open gaps
A13: IA-001 | B13: Parent Registration & Login | C13: ='Requirement Match'!H2 -> 0.85 | D13: Substantial | E13: High | F13: =COUNTIF('Gap Register'!$B$2:$B$500,A13) -> 4
A14: IA-002 | B14: Parent Profile Onboarding | C14: ='Requirement Match'!H3 -> 0.92857143 | D14: Substantial | E14: High | F14: =COUNTIF('Gap Register'!$B$2:$B$500,A14) -> 3
A15: IA-003 | B15: Account Security & Lifecycle | C15: ='Requirement Match'!H4 -> 0.76666667 | D15: Substantial | E15: High | F15: =COUNTIF('Gap Register'!$B$2:$B$500,A15) -> 5
A16: LP-001 | B16: Learner Profile Creation | C16: ='Requirement Match'!H5 -> 0.94230769 | D16: Substantial | E16: High | F16: =COUNTIF('Gap Register'!$B$2:$B$500,A16) -> 3
A17: LP-002 | B17: Learner Profile Correction | C17: ='Requirement Match'!H6 -> 0.96 | D17: Substantial | E17: High | F17: =COUNTIF('Gap Register'!$B$2:$B$500,A17) -> 3
A18: LP-004 | B18: Learner Selection & Active Session Control | C18: ='Requirement Match'!H7 -> 0.77777778 | D18: Substantial / Regressed | E18: High | F18: =COUNTIF('Gap Register'!$B$2:$B$500,A18) -> 7
A19: AR-001 | B19: Canonical App Registry | C19: ='Requirement Match'!H8 -> 0.96666667 | D19: Substantial | E19: High | F19: =COUNTIF('Gap Register'!$B$2:$B$500,A19) -> 3
A20: AN-001 | B20: Minimal-Data Daily Analytics | C20: ='Requirement Match'!H9 -> 0.94285714 | D20: Substantial | E20: High | F20: =COUNTIF('Gap Register'!$B$2:$B$500,A20) -> 3
A21: AR-002 | B21: Automated App Deployment & Release Safety | C21: ='Requirement Match'!H10 -> 0.5 | D21: Partial | E21: Medium | F21: =COUNTIF('Gap Register'!$B$2:$B$500,A21) -> 10
A22: LA-001 | B22: Secure Cross-Domain App Launch | C22: ='Requirement Match'!H11 -> 0.8 | D22: Substantial / Partial Integration | E22: Medium-High | F22: =COUNTIF('Gap Register'!$B$2:$B$500,A22) -> 6
A23: LA-002 | B23: Session-Bound API Authorization | C23: ='Requirement Match'!H12 -> 0.725 | D23: Substantial / Contract Gap | E23: High | F23: =COUNTIF('Gap Register'!$B$2:$B$500,A23) -> 6
A24: LA-003 | B24: Compact Progress Persistence | C24: ='Requirement Match'!H13 -> 0.8 | D24: Substantial / Partial Amendments | E24: Medium-High | F24: =COUNTIF('Gap Register'!$B$2:$B$500,A24) -> 6
... A32: EN-002 | B32: Effective App Access & Overlap Control | C32: ='Requirement Match'!H21 -> 0.4875 | D32: Partial | E32: High | F32: =COUNTIF('Gap Register'!$B$2:$B$500,A32) -> 7

Sheet Requirement Match
A1: Requirement ID | B1: Requirement Title | C1: Acceptance Criteria / Tests | D1: Full Match | E1: Partial Match | F1: Missing / Contradicted | G1: Weighted Points | H1: Match % | I1: Implementation Stage | J1: Confidence | K1: Key Gap Summary | L1: Gap Count
A2: IA-001 | B2: Parent Registration & Login | C2: 10 | D2: 7 | E2: 3 | F2: 0 | G2: =D2+0.5*E2 -> 8.5 | H2: =G2/C2 -> 0.85 | I2: Substantial | J2: High | K2: Core behavior works locally; production Supabase Auth/email delivery/shared rate-limit contract is not active. | L2: =COUNTIF('Gap Register'!$B$2:$B$500,A2) -> 4
A3: IA-002 | B3: Parent Profile Onboarding | C3: 14 | D3: 12 | E3: 2 | F3: 0 | G3: =D3+0.5*E3 -> 13 | H3: =G3/C3 -> 0.92857143 | I3: Substantial | J3: High | K3: Strong local match; remaining deductions are production Supabase/RLS and real invoice-delivery integration. | L3: =COUNTIF('Gap Register'!$B$2:$B$500,A3) -> 3
A4: IA-003 | B4: Account Security & Lifecycle | C4: 15 | D4: 10 | E4: 3 | F4: 2 | G4: =D4+0.5*E4 -> 11.5 | H4: =G4/C4 -> 0.76666667 | I4: Substantial | J4: High | K4: Raw email-change token is stored locally; Supabase email-change configuration and full session revocation are incomplete. | L4: =COUNTIF('Gap Register'!$B$2:$B$500,A4) -> 5
A5: LP-001 | B5: Learner Profile Creation | C5: 26 | D5: 23 | E5: 3 | F5: 0 | G5: =D5+0.5*E5 -> 24.5 | H5: =G5/C5 -> 0.94230769 | I5: Substantial | J5: High | K5: Core profile rules are strong; passkey-dependent paths, production RLS and billing integration are not end-to-end. | L5: =COUNTIF('Gap Register'!$B$2:$B$500,A5) -> 3
A6: LP-002 | B6: Learner Profile Correction | C6: 25 | D6: 23 | E6: 2 | F6: 0 | G6: =D6+0.5*E6 -> 24 | H6: =G6/C6 -> 0.96 | I6: Substantial | J6: High | K6: Core update/version/idempotency behavior is strong; commercial/session integration is not production-complete. | L6: =COUNTIF('Gap Register'!$B$2:$B$500,A6) -> 3
A7: LP-004 | B7: Learner Selection & Active Session Control | C7: 45 | D7: 32 | E7: 6 | F7: 7 | G7: =D7+0.5*E7 -> 35 | H7: =G7/C7 -> 0.77777778 | I7: Substantial / Regressed | J7: High | K7: Latest v45 removes repeated-interruption auto-completion, but code still supports it; browser-runtime/passkey gaps remain. | L7: =COUNTIF('Gap Register'!$B$2:$B$500,A7) -> 7
A8: AR-001 | B8: Canonical App Registry | C8: 30 | D8: 28 | E8: 2 | F8: 0 | G8: =D8+0.5*E8 -> 29 | H8: =G8/C8 -> 0.96666667 | I8: Substantial | J8: High | K8: Registry lifecycle is strong; production Supabase/RLS and billing-side remediation integration remain. | L8: =COUNTIF('Gap Register'!$B$2:$B$500,A8) -> 3
A9: AN-001 | B9: Minimal-Data Daily Analytics | C9: 35 | D9: 32 | E9: 2 | F9: 1 | G9: =D9+0.5*E9 -> 33 | H9: =G9/C9 -> 0.94285714 | I9: Substantial | J9: High | K9: Analytics design is strong; production scheduler/service identity and runtime-store deployment are incomplete. | L9: =COUNTIF('Gap Register'!$B$2:$B$500,A9) -> 3
A10: AR-002 | B10: Automated App Deployment & Release Safety | C10: 44 | D10: 17 | E10: 10 | F10: 17 | G10: =D10+0.5*E10 -> 22 | H10: =G10/C10 -> 0.5 | I10: Partial | J10: Medium | K10: Deployment primitives exist, but provider discovery, CI provenance, immutable promotion, compatibility and rollback automation are incomplete. | L10: =COUNTIF('Gap Register'!$B$2:$B$500,A10) -> 10
A11: LA-001 | B11: Secure Cross-Domain App Launch | C11: 40 | D11: 29 | E11: 6 | F11: 5 | G11: =D11+0.5*E11 -> 32 | H11: =G11/C11 -> 0.8 | I11: Substantial / Partial Integration | J11: Medium-High | K11: Launch flow exists; machine identity is shared-secret based and SC-003 provisional launch + full cross-domain production integration are incomplete. | L11: =COUNTIF('Gap Register'!$B$2:$B$500,A11) -> 6
A12: LA-002 | B12: Session-Bound API Authorization | C12: 40 | D12: 25 | E12: 8 | F12: 7 | G12: =D12+0.5*E12 -> 29 | H12: =G12/C12 -> 0.725 | I12: Substantial / Contract Gap | J12: High | K12: Short-lived EdDSA access token is strong, but starting sessions incorrectly receive an active broad-scope grant instead of provisional usable-launch-only grant. | L12: =COUNTIF('Gap Register'!$B$2:$B$500,A12) -> 6
A13: LA-003 | B13: Compact Progress Persistence | C13: 40 | D13: 29 | E13: 6 | F13: 5 | G13: =D13+0.5*E13 -> 32 | H13: =G13/C13 -> 0.8 | I13: Substantial / Partial Amendments | J13: Medium-High | K13: Core current-row/versioned progress is present; newer progress migration/recovery/summary amendments are not fully implemented. | L13: =COUNTIF('Gap Register'!$B$2:$B$500,A13) -> 6
... A21: EN-002 | B21: Effective App Access & Overlap Control | C21: 40 | D21: 16 | E21: 7 | F21: 17 | G21: =D21+0.5*E21 -> 19.5 | H21: =G21/C21 -> 0.4875 | I21: Partial | J21: High | K21: Period overlap/effective state exists; checkout/payment lifecycle, grace/cancellation and resume-across-paid-end behavior do not match v45. | L21: =COUNTIF('Gap Register'!$B$2:$B$500,A21) -> 7

Sheet Gap Register
A1: Gap ID | B1: Requirement ID | C1: Severity | D1: Category | E1: Acceptance / Rule | F1: Gap Description | G1: Evidence / Reason | H1: Recommended Fix | I1: Code Evidence URL | J1: Requirements Source | K1: Status | L1: Resolution Notes
A2: GAP-001 | B2: IA-001 | C2: High | D2: Production runtime | E2: AC1-AC7 / runtime contract | F2: Production identity path is not Supabase Auth. | G2: README states current runtime is local SQLite + built-in session auth; Supabase helpers/migrations are dormant. | H2: Implement and activate SupabaseAuthAdapter in production, preserving stable parent IDs and current adapter contract. | I2: https://github.com/SridharVoleti/babystepsindia/blob/master/README.md | J2: Babysteps_Platform_Requirements_v45.xlsx | K2: Deferred | L2: Deferred - platform: requires activating Supabase Auth in production (current runtime is local SQLite + built-in session auth by design, see README).
A3: GAP-002 | B3: IA-001 | C3: Medium | D3: Email delivery | E3: AC3, AC7 | F3: Verification/reset delivery is a development URL rather than configured production email delivery. | G3: Server actions return verificationUrl/resetUrl for local development. | H3: Wire Supabase/custom SMTP templates and callbacks; never expose verification/reset links in production UI responses. | I3: https://github.com/SridharVoleti/babystepsindia/blob/master/src/app/(auth)/actions.ts | J3: Babysteps_Platform_Requirements_v45.xlsx | K3: Deferred | L3: Deferred - platform: requires configuring production email delivery (Supabase/custom SMTP callbacks); same root cause as GAP-001/004.
A4: GAP-003 | B4: IA-001 | C4: Medium | D4: Rate limiting | E4: Security/NFR | F4: Rate limiter is process-local and will not enforce limits consistently across multiple Vercel instances. | G4: README describes in-memory fixed-window rate limiting as single-process only. | H4: Move auth rate limits to a shared durable store or provider-native rate limiter before scale-out. | I4: https://github.com/SridharVoleti/babystepsindia/blob/master/README.md | J4: Babysteps_Platform_Requirements_v45.xlsx | K4: Deferred | L4: Deferred - platform: requires a shared durable store (Redis/Vercel KV) for cross-instance rate limiting; current in-memory limiter is correct for single-process.
A5: GAP-004 | B5: IA-001 | C5: Medium | D5: Production verification | E5: AC3-AC9 | F5: Production Supabase session/email-verification behavior is not exercised end-to-end. | G5: Current tests primarily validate the SQLite adapter and local cookie flow. | H5: Add Supabase integration/E2E tests for signup, verify, reset, suspended/deleted gating and recovery upsert. | I5: https://github.com/SridharVoleti/babystepsindia/blob/master/README.md | J5: Babysteps_Platform_Requirements_v45.xlsx | K5: Deferred | L5: Deferred - platform: requires a live Supabase project to exercise production auth/session/email flows end-to-end.
A6: GAP-005 | B6: IA-002 | C6: Medium | D6: Production runtime | E6: AC1-AC14 | F6: Parent onboarding runs on the local SQLite/auth stack rather than the frozen Supabase production stack. | G6: README marks Supabase production path dormant. | H6: Port transactional profile+consent update to Supabase/Postgres and validate RLS/authorization. | I6: https://github.com/SridharVoleti/babystepsindia/blob/master/README.md | J6: Babysteps_Platform_Requirements_v45.xlsx | K6: Deferred | L6: Deferred - platform: requires porting parent onboarding to the production Supabase/Postgres stack.
A7: GAP-006 | B7: IA-002 | C7: Low | D7: Billing integration | E7: AC11-AC12 | F7: Invoice recipient/delivery behavior is implemented as local metadata utility, not proven against a real billing/invoice provider. | G7: Identity code can compute labels, but BI billing requirements/providers are not implemented. | H7: Integrate the label/email contract with the billing/invoice producer and add contract tests. | I7: https://github.com/SridharVoleti/babystepsindia/blob/master/README.md | J7: Babysteps_Platform_Requirements_v45.xlsx | K7: Deferred | L7: Deferred - platform: requires a real billing/invoice provider (BI requirements not yet built).
A8: GAP-007 | B8: IA-002 | C8: Medium | D8: Authorization/RLS | E8: Security | F8: Production row-level protection of phone/profile data is not demonstrated. | G8: Current runtime relies on application guards over SQLite. | H8: Implement Supabase RLS policies and integration tests for parent/support/admin read boundaries. | I8: https://github.com/SridharVoleti/babystepsindia/blob/master/README.md | J8: Babysteps_Platform_Requirements_v45.xlsx | K8: Deferred | L8: Deferred - platform: requires Supabase RLS policies on a live Postgres project.
A9: GAP-008 | B9: IA-003 | C9: Critical | D9: Credential security | E9: AC15 | F9: Email-change verification token is stored raw in a platform table. | G9: requestEmailChange inserts token directly into email_change_requests; resend also replaces the raw token. | H9: Use provider-managed token/nonce or store only a one-way hash; never persist the raw verification token. | I9: https://github.com/SridharVoleti/babystepsindia/blob/master/src/lib/db/account-security-repo.ts | J9: Babysteps_Platform_Requirements_v45.xlsx | K9: Resolved | L9: Resolved 2026-08-08: email-change verification token is now sha256-hashed (token_hash column) - raw token never persisted. src/lib/db/account-security-repo.ts, src/lib/db/schema.sql.
A10: GAP-009 | B10: IA-003 | C10: High | D10: Supabase configuration | E10: AC4-AC8 | F10: Secure Email Change / 86,400-second Supabase email-link expiry is not configured in the active runtime. | G10: Code comment explicitly says equivalent Supabase Auth project setting still needs configuring. | H10: Configure Supabase Auth exactly as frozen and add deployment/configuration assertions. | I10: https://github.com/SridharVoleti/babystepsindia/blob/master/src/lib/db/account-security-repo.ts | J10: Babysteps_Platform_Requirements_v45.xlsx | K10: Deferred | L10: Deferred - platform: requires configuring Supabase Auth project settings (email-link expiry) directly.
A11: GAP-010 | B11: IA-003 | C11: High | D11: Session revocation | E11: AC11 | F11: Soft delete does not explicitly atomically revoke every learner session and app grant in the shown transaction. | G11: softDeleteAccount updates profile and learner unlock contexts; no direct learner_sessions/app_session_grants revocation appears in that transaction. | H11: Add authoritative transactional revocation of parent sessions, learner sessions, launch state and app grants. | I11: https://github.com/SridharVoleti/babystepsindia/blob/master/src/lib/db/account-security-repo.ts | J11: Babysteps_Platform_Requirements_v45.xlsx | K11: Resolved | L11: Resolved 2026-08-08: softDeleteAccount now atomically revokes every active/starting learner session and its app grant via new revokeActiveLearnerSessionsForParent, in the same transaction. src/lib/learning-session/gateway.ts, src/lib/db/account-security-repo.ts.
A12: GAP-011 | B12: IA-003 | C12: Medium | D12: Privacy logging | E12: Security / AC15 | F12: Email-change account-event metadata stores old/new email values. | G12: finalizeEmailChange records oldEmail/newEmail in account_events metadata. | H12: Store minimized identifiers/change type only; mask or omit raw email values from routine audit/log payloads. | I12: https://github.com/SridharVoleti/babystepsindia/blob/master/src/lib/db/account-security-repo.ts | J12: Babysteps_Platform_Requirements_v45.xlsx | K12: Resolved | L12: Resolved 2026-08-08: account_events for email_change_requested/verified now store maskEmail() output, not raw addresses (parent_email_history keeps the full archival record per its own append-only rule). src/lib/db/account-security-repo.ts.
... A108: GAP-107 | B108: EN-002 | C108: Medium | D108: Lifecycle versioning | E108: AT-EN-002-34 | F108: effective_version bumps only when period/role source-set hash changes, not necessarily on all lifecycle state changes such as grace/cancel. | G108: source_set_hash contains only period IDs and roles; missing lifecycle overlays cannot bump it. | H108: Include authoritative lifecycle source/version in effective decision version and invalidate caches on every relevant event. | I108: https://github.com/SridharVoleti/babystepsindia/blob/master/src/lib/entitlement-access/service.ts | J108: Babysteps_Platform_Requirements_v45.xlsx | K108: Deferred | L108: Deferred - platform: requires EN-003 lifecycle overlays (grace/cancel) driven by a BI producer that does not exist; same root cause as GAP-093/097/103/104.

Sheet Scoring & Scope
A1: Scoring Method, Scope & Audit Caveats
A4: Item | B4: Definition | F4: Source | G4: Value | H4: Notes
A5: Full Match | B5: 1.0 point — inspected implementation materially satisfies the frozen behavior/constraint. | F5: Requirements | G5: Babysteps_Platform_Requirements_v45.xlsx | H5: Frozen acceptance source
A6: Partial Match | B6: 0.5 point — core behavior exists but production runtime, dependency, edge case or contract is incomplete. | F6: Repository | G6: https://github.com/SridharVoleti/babystepsindia | H6: Audited codebase
A7: Missing / Contradicted | B7: 0 points — required behavior is absent or implementation conflicts with v45. | F7: Branch | G7: master | H7: Default branch
A8: Formula | B8: Match % = (Full + 0.5 × Partial) / Acceptance Criteria or approved acceptance-test count. | F8: HEAD | G8: 517e3cf3ef141908679742ef2abb60dd93b32400 | H8: Audited repository state
A9: Audit type | B9: Static repository audit against v45. It is not a production certification or a substitute for executing the complete acceptance suite. | F9: Runtime note | G9: README: local SQLite + built-in auth | H9: Major recurring production-contract deduction
A10: Gap coverage | B10: Gap Register lists every distinct gap identified during this static review; shared architectural gaps are repeated where they materially reduce a requirement score.
A13: Included Requirement | B13: Why Included | C13: Implementation Signal | D13: Excluded / Not Scored
A14: IA-001/002/003 | B14: Explicit auth/profile/security implementation and tests | C14: README, routes, repos, migrations | D14: IA-004 — no WebAuthn implementation found
A15: LP-001/002/004 | B15: Explicit learner/session services and tests | C15: Learner routes/repos, session services, migrations | D15: New BB-10 launcher requirements — no explicit v45 implementation slice at audited HEAD
A16: AR-001 | B16: Explicit app registry implementation/tests | C16: Admin app registry services/migrations | D16: —
A17: AN-001 | B17: Explicit analytics implementation/tests | C17: Analytics buffer/jobs/admin routes | D17: Other analytics requirements not implemented
A18: AR-002 | B18: Meaningful deployment primitives exist | C18: Deployment services/routes/tests | D18: Scored as Partial, not as completed
A19: LA-001/002/003/004 | B19: Explicit launch/auth/progress/finalization services/tests | C19: App launch/grant/progress/finalization modules | D19: —
A20: AU-001/002 | B20: Explicit policy/mode services/tests | C20: authorization/modes and action catalog | D20: AU-004 — machine identity contract not implemented
A21: SC-001/002/003 | B21: Explicit runtime/credits/start contracts and server pieces | C21: Session/credit/start services/tests | D21: SC-001 browser SDK itself remains partial
A22: EN-001/002 | B22: Explicit entitlement-cycle/access services/tests | C22: entitlement-cycle/access modules | D22: EN-003 lifecycle events not implemented
A23: Billing BI-* / Progress PR-* | B23: Not scored | C23: No complete implementation slice found | D23: These appear as dependencies/gaps where they reduce an implemented requirement's match
