Workbook

Sheet 00_Workbook_Guide
A1: Babysteps Platform Requirements Workbook
A3: Item | B3: Specification
A4: Purpose | B4: Implementation-ready requirements specification for Codex-assisted development of the Babysteps platform and its learning-app integrations.
A5: Approval rule | B5: A requirement is added to 02_Requirements only after it has been visualized and explicitly approved.
A6: Priority model | B6: Must Have = required for the target release. Should Have = valuable but may follow after the must-have foundation.
A7: Requirement granularity | B7: Each row must describe one independently testable behavior or constraint.
A8: Traceability | B8: Requirement IDs connect UX flows, API contracts, data-model entries, acceptance tests, and implementation notes.
A9: Platform boundary | B9: Babysteps owns identity, parent-owned learner profiles, app access, purchaser-parent subscriptions, shared engagement, progress persistence, privacy and administration.
A10: Codex readiness | B10: A requirement is Codex Ready only when 09_Codex_Build_Specs contains an Approved exact build packet covering runtime assumptions, functional contract, UI, migrations, APIs, validation, authorization, security, errors, idempotency, telemetry, tests, explicit non-goals, files/modules and definition of done.
A11: Codex readiness | B11: A requirement is Codex Ready only when behavior, acceptance criteria, dependencies, data/API impact, edge cases, and security expectations are complete.
A12: Current stage | B12: Twelve active requirements are frozen and Codex Ready. BB-04 is 2/4 complete: secure one-time app launch and short-lived dual-proof backend API authorization with no browser token or refresh token.
A13: Commercial and cadence constraints | B13: Every subscription is purchased by one parent and assigned to one learner. Products may grant one app or a bundle. Each entitled learner receives two learning sessions per week independently in each entitled app.
A14: Step-by-step workflow
A15: 1 | B15: Select one feature group | C15: Define the learner/business outcome
A16: 2 | B16: Visualize proposed requirements in chat | C16: Show actors, screens, states, rules, data and edge cases
A17: 3 | B17: Challenge and refine | C17: Remove duplication, hidden complexity and app/platform boundary violations
A18: 4 | B18: Approve individual requirements | C18: Confirm Must Have or Should Have
A19: 5 | B19: Write approved requirements | C19: Populate requirement, UX, API, data and test sheets
A20: 6 | B20: Generate Codex build packet | C20: Export a coherent development slice with dependencies and tests
A22: This workbook is intentionally empty of product requirements until each requirement is visualized and approved.

Sheet 01_Dashboard
A1: Babysteps Requirements Dashboard
A3: Portfolio metric | B3: Current | D3: Building block | E3: Planned | F3: Frozen | G3: Remaining | H3: Complete
A4: Frozen requirements | B4: 12 | D4: ='01A_Requirement_Roadmap'!D5 -> Identity and authentication | E4: ='01A_Requirement_Roadmap'!E5 -> 4 | F4: ='01A_Requirement_Roadmap'!F5 -> 4 | G4: ='01A_Requirement_Roadmap'!G5 -> 0 | H4: ='01A_Requirement_Roadmap'!H5 -> 1
A5: Remaining requirements | B5: 62 | D5: ='01A_Requirement_Roadmap'!D6 -> Learner profiles and guardians | E5: ='01A_Requirement_Roadmap'!E6 -> 3 | F5: ='01A_Requirement_Roadmap'!F6 -> 3 | G5: ='01A_Requirement_Roadmap'!G6 -> 0 | H5: ='01A_Requirement_Roadmap'!H6 -> 1
A6: Planned requirements | B6: 74 | D6: ='01A_Requirement_Roadmap'!D7 -> App registry | E6: ='01A_Requirement_Roadmap'!E7 -> 2 | F6: ='01A_Requirement_Roadmap'!F7 -> 2 | G6: ='01A_Requirement_Roadmap'!G7 -> 0 | H6: ='01A_Requirement_Roadmap'!H7 -> 1
A7: Overall completion | B7: 0.16216216 | D7: ='01A_Requirement_Roadmap'!D8 -> App launch and single sign-on | E7: ='01A_Requirement_Roadmap'!E8 -> 4 | F7: ='01A_Requirement_Roadmap'!F8 -> 2 | G7: ='01A_Requirement_Roadmap'!G8 -> 2 | H7: ='01A_Requirement_Roadmap'!H8 -> 0.5
A8: Must Haves frozen | B8: 11 | D8: ='01A_Requirement_Roadmap'!D9 -> Authorization | E8: ='01A_Requirement_Roadmap'!E9 -> 4 | F8: ='01A_Requirement_Roadmap'!F9 -> 3 | G8: ='01A_Requirement_Roadmap'!G9 -> 1 | H8: ='01A_Requirement_Roadmap'!H9 -> 0.75
A9: Should Haves frozen | B9: 0 | D9: ='01A_Requirement_Roadmap'!D10 -> Active session control | E9: ='01A_Requirement_Roadmap'!E10 -> 3 | F9: ='01A_Requirement_Roadmap'!F10 -> 3 | G9: ='01A_Requirement_Roadmap'!G10 -> 0 | H9: ='01A_Requirement_Roadmap'!H10 -> 1
A10: Codex Ready | B10: 12 | D10: ='01A_Requirement_Roadmap'!D11 -> Billing and subscriptions | E10: ='01A_Requirement_Roadmap'!E11 -> 5 | F10: ='01A_Requirement_Roadmap'!F11 -> 5 | G10: ='01A_Requirement_Roadmap'!G11 -> 0 | H10: ='01A_Requirement_Roadmap'!H11 -> 1
A11: Building blocks complete | B11: 3 | D11: ='01A_Requirement_Roadmap'!D12 -> Entitlements and app access | E11: ='01A_Requirement_Roadmap'!E12 -> 4 | F11: ='01A_Requirement_Roadmap'!F12 -> 4 | G11: ='01A_Requirement_Roadmap'!G12 -> 0 | H11: ='01A_Requirement_Roadmap'!H12 -> 1
A12: Building blocks in progress | B12: 2 | D12: ='01A_Requirement_Roadmap'!D13 -> Progress storage and synchronization | E12: ='01A_Requirement_Roadmap'!E13 -> 5 | F12: ='01A_Requirement_Roadmap'!F13 -> 4 | G12: ='01A_Requirement_Roadmap'!G13 -> 1 | H12: ='01A_Requirement_Roadmap'!H13 -> 0.8
A13: Nice to Haves frozen | B13: =COUNTIFS('02_Requirements'!$F$2:$F$1000,"Nice to Have",'02_Requirements'!$G$2:$G$1000,"Approved") -> 1 | D13: ='01A_Requirement_Roadmap'!D14 -> Unified learner launcher | E13: ='01A_Requirement_Roadmap'!E14 -> 4 | F13: ='01A_Requirement_Roadmap'!F14 -> 1 | G13: ='01A_Requirement_Roadmap'!G14 -> 3 | H13: ='01A_Requirement_Roadmap'!H14 -> 0.25
A14: Deferred requirements | B14: =COUNTIF('02_Requirements'!$G$2:$G$1000,"Deferred") -> 7 | D14: ='01A_Requirement_Roadmap'!D15 -> Engagement and gamification | E14: ='01A_Requirement_Roadmap'!E15 -> 6 | F14: ='01A_Requirement_Roadmap'!F15 -> 0 | G14: ='01A_Requirement_Roadmap'!G15 -> 6 | H14: ='01A_Requirement_Roadmap'!H15 -> 0
D15: ='01A_Requirement_Roadmap'!D16 -> Parent dashboard | E15: ='01A_Requirement_Roadmap'!E16 -> 4 | F15: ='01A_Requirement_Roadmap'!F16 -> 0 | G15: ='01A_Requirement_Roadmap'!G16 -> 4 | H15: ='01A_Requirement_Roadmap'!H16 -> 0
D16: ='01A_Requirement_Roadmap'!D17 -> Notifications and reminders | E16: ='01A_Requirement_Roadmap'!E17 -> 3 | F16: ='01A_Requirement_Roadmap'!F17 -> 0 | G16: ='01A_Requirement_Roadmap'!G17 -> 3 | H16: ='01A_Requirement_Roadmap'!H17 -> 0
D17: ='01A_Requirement_Roadmap'!D18 -> Administration and support | E17: ='01A_Requirement_Roadmap'!E18 -> 5 | F17: ='01A_Requirement_Roadmap'!F18 -> 0 | G17: ='01A_Requirement_Roadmap'!G18 -> 5 | H17: ='01A_Requirement_Roadmap'!H18 -> 0
D18: ='01A_Requirement_Roadmap'!D19 -> Privacy, consent and child safety | E18: ='01A_Requirement_Roadmap'!E19 -> 5 | F18: ='01A_Requirement_Roadmap'!F19 -> 0 | G18: ='01A_Requirement_Roadmap'!G19 -> 5 | H18: ='01A_Requirement_Roadmap'!H19 -> 0
D19: ='01A_Requirement_Roadmap'!D20 -> Analytics and observability | E19: ='01A_Requirement_Roadmap'!E20 -> 4 | F19: ='01A_Requirement_Roadmap'!F20 -> 1 | G19: ='01A_Requirement_Roadmap'!G20 -> 3 | H19: ='01A_Requirement_Roadmap'!H20 -> 0.25
D20: ='01A_Requirement_Roadmap'!D21 -> Developer platform and SDK | E20: ='01A_Requirement_Roadmap'!E21 -> 5 | F20: ='01A_Requirement_Roadmap'!F21 -> 0 | G20: ='01A_Requirement_Roadmap'!G21 -> 5 | H20: ='01A_Requirement_Roadmap'!H21 -> 0
D21: ='01A_Requirement_Roadmap'!D22 -> Backup, recovery and deployment safety | E21: ='01A_Requirement_Roadmap'!E22 -> 4 | F21: ='01A_Requirement_Roadmap'!F22 -> 0 | G21: ='01A_Requirement_Roadmap'!G22 -> 4 | H21: ='01A_Requirement_Roadmap'!H22 -> 0

Sheet 02_Requirements
A1: Requirement ID | B1: Epic ID | C1: Domain | D1: Feature Group | E1: Requirement Title | F1: Priority | G1: Approval Status | H1: Codex Ready | I1: Delivery Status | J1: Requirement Type | K1: Ownership Layer | L1: Primary Actor | M1: User Story | N1: Functional Requirement | O1: Business Rules | P1: Preconditions | Q1: Trigger | R1: Main Flow | S1: Alternate / Error Flows | T1: Data Inputs | U1: Data Outputs | V1: UI / UX Specification | W1: API / Service Contract | X1: Data Model Impact | Y1: Security & Privacy | Z1: Non-Functional Requirements | AA1: Acceptance Criteria Summary | AB1: Dependencies | AC1: Duolingo Inspiration | AD1: Source URL | AE1: Codex Implementation Notes | AF1: Test IDs | AG1: Version | AH1: Owner | AI1: Last Updated
A2: IA-001 | B2: EP-IDENTITY-01 | C2: Identity & Access | D2: Parent Registration & Login | E2: Email-and-password parent registration and login | F2: Must Have | G2: Approved | H2: Yes | I2: Done | J2: Functional | K2: Babysteps Platform | L2: Parent | M2: As a parent, I want to register and sign in using my email address and password so that I can securely access Babysteps and manage my children's learning profiles. | N2: Babysteps shall support parent account registration and login using only email address and password in Version 1. Immediately after Supabase Auth successfully creates the user, the platform shall create exactly one parent profile linked one-to-one with that Auth user. The profile may exist while email verification is pending, but protected parent and learner data shall remain inaccessible until the email is verified. Profile creation shall be idempotent and recoverable. | O2: 1. Version 1 supports email and password only; Google, Apple, phone and magic-link authentication are excluded. 2. Email is the unique login identifier and is normalized before submission. 3. Password storage, hashing and verification remain entirely within Supabase Auth. 4. A parent profile is created immediately after the Auth user is created. 5. Email verification is required before protected parent or learner data can be accessed. 6. One Supabase Auth user maps to exactly one parent profile. 7. Repeated signup callbacks, triggers, refreshes or recovery calls must not create duplicate parent profiles. 8. Suspended or deleted profiles cannot access protected resources. 9. A child learner does not require an Auth user or email account. | P2: The visitor is not authenticated. The Babysteps Supabase project, authentication email provider and callback URLs are configured. | Q2: The visitor submits the registration form or login form. | R2: Registration: 1. Parent enters email, password and password confirmation. 2. Client and server validate the inputs. 3. Supabase Auth creates the authentication identity. 4. A database trigger or trusted server process creates the parent profile immediately with onboarding_status='profile_pending'. 5. A verification email is sent. 6. Parent verifies the email. 7. On first verified access, Babysteps confirms the existing profile and continues to parent-profile onboarding. Login: 1. Parent enters email and password. 2. Supabase Auth validates the credentials. 3. Babysteps checks email verification and parent profile status. 4. If the profile is unexpectedly missing, a recovery upsert creates it safely. 5. Parent enters the account area or resumes the next incomplete onboarding step. | S2: Existing email: direct the parent to Sign in or Forgot password without creating another account. Weak or invalid password: preserve the email and show validation feedback. Expired verification link: permit resend subject to rate limits. Profile creation interruption: retry the idempotent profile upsert on the next authenticated request. Incorrect credentials: show a generic authentication error. Suspended profile: deny protected access and show the support route. Expired session: return to sign-in and preserve the intended destination when safe. | T2: Registration inputs: email, password, password confirmation, accepted terms version and accepted privacy version. Login inputs: email and password. System context: Supabase Auth user ID, email verification status, locale and timezone defaults. | U2: Supabase Auth identity; exactly one parent profile created at registration; verification-pending or verified authentication state; onboarding status; authenticated session after verification; audit events for signup, profile creation, verification, login success/failure, password reset and logout. | V2: Separate Sign up and Sign in screens. Explicit Email, Password and Confirm password labels. Show/hide password control. Visible password requirements. Inline validation and loading state. Non-enumerating error messages. Post-registration verification-required screen. First verified login continues to onboarding rather than asking the user to register again. No Google, Apple, phone or magic-link controls in Version 1. | W2: Supabase Auth operations: - signUp(email, password) - signInWithPassword(email, password) - signOut() - resetPasswordForEmail(email) - updateUser(password) Profile creation: - Preferred: an idempotent database trigger on auth.users INSERT creates public.profiles using NEW.id. - Recovery endpoint: POST /v1/onboarding/ensure-parent-profile verifies the authenticated user and safely creates the profile only when it is missing. Protected routes require a verified Supabase session and an active parent profile. | X2: profiles table: - id uuid primary key referencing auth.users(id) on delete cascade - profile_type text default 'parent' - display_name text nullable until onboarding - account_status text - onboarding_status text default 'profile_pending' - locale text - timezone text - created_at timestamptz - updated_at timestamptz Allowed onboarding_status values: - profile_pending - learner_pending - complete Create an idempotent auth.users INSERT trigger that inserts the profile with ON CONFLICT DO NOTHING. Retain a server-side recovery upsert for repair and testability. | Y2: Passwords, password hashes and authentication tokens must never be stored in Babysteps tables or logs. Service-role credentials remain server-side. Require HTTPS and secure session cookies. Rate-limit signup, login, verification resend and password reset. Avoid account-enumeration messages. Require verified email before protected access. Record privacy and terms acceptance separately with policy version and timestamp. | Z2: Registration and login p95 server response under 2 seconds, excluding external email delivery. All flows keyboard accessible and usable at 320px width. Duplicate profile creation rate must be zero. Failures show a clear retry path. Logs include request IDs but exclude passwords and tokens. | AA2: AC1 Parent can register with a valid email and compliant password. AC2 Successful Auth registration immediately creates exactly one parent profile. AC3 A verification email is sent and protected data remains inaccessible until verification. AC4 First verified access uses the existing parent profile rather than creating another. AC5 Replayed triggers, callbacks and recovery calls do not create duplicate profiles. AC6 Parent can sign in and sign out. AC7 Parent can request and complete a password reset. AC8 Incorrect credentials do not reveal whether the email exists. AC9 Suspended or deleted profiles are denied protected access. AC10 No social, phone or magic-link authentication control appears in Version 1. | AB2: Supabase Auth configuration; custom SMTP before scaled onboarding; profiles migration; consent/privacy policy versions; authenticated route middleware; email templates. | AC2: Babysteps retains low-friction onboarding but deliberately uses a simpler email-password identity model for Version 1. | AE2: Implement the Auth UI and server actions as a reusable Babysteps identity module. Keep authentication behind an AuthAdapter interface so future providers can be added without changing parent IDs. Use shared input schemas for email/password validation. Create the parent profile from an idempotent auth.users INSERT trigger. Keep POST /v1/onboarding/ensure-parent-profile as a recovery operation and safe authenticated read. Redirect by onboarding_status after verification: - profile_pending -> parent profile completion - learner_pending -> add or select learner - complete -> dashboard Exact build packet: 09_Codex_Build_Specs!CBS-IA-001 | AF2: AT-IA-001-01, AT-IA-001-02, AT-IA-001-03, AT-IA-001-04, AT-IA-001-05, AT-IA-001-06, AT-IA-001-07, AT-IA-001-08, AT-IA-001-09 | AG2: 1.0 | AH2: Product Owner | AI2: 2026-07-30
A3: IA-002 | B3: EP-IDENTITY-01 | C3: Identity & Access | D3: Parent Profile Onboarding | E3: Mandatory parent mobile number with optional display name | F3: Must Have | G3: Approved | H3: Yes | I3: Done | J3: Functional | K3: Babysteps Platform | L3: Parent | M3: As a registered parent, I want to complete a minimal parent profile so that Babysteps can identify and contact me without collecting unnecessary personal information. | N3: After email verification, Babysteps shall require the parent to complete the existing parent profile by supplying a valid mobile number. The display name shall be optional. Mobile numbers shall be format-validated and normalized only; Version 1 shall not send or require an SMS OTP. Postal address and parent date of birth shall not be collected. Invoices and receipts shall be delivered to the authenticated email address. The invoice recipient label shall use the display name when present and the email address when the display name is absent. | O3: 1. The parent profile already exists before onboarding begins. 2. Mobile number is mandatory before the parent can continue to learner setup. 3. Mobile number must be parsed and validated using the selected country or calling code. 4. Store the normalized mobile number in E.164 format. 5. Version 1 performs format validation only; it does not send an SMS OTP and does not mark the number as verified. 6. Mobile number does not have to be globally unique because family members may share a contact number. 7. Display name is optional and may be blank. 8. Email is read-only and comes from Supabase Auth. 9. Postal address, parent date of birth and legal name are not collected in Version 1. 10. Invoices and receipts are sent to the authenticated email address. 11. Invoice recipient label uses display name when present; otherwise it uses the authenticated email address. 12. Mobile number use for marketing or SMS requires separate consent and is outside this requirement. 13. Successful completion changes onboarding_status from profile_pending to learner_pending. 14. Repeated submissions update the same profile and do not create duplicate consent records. | P3: The parent has a verified Supabase session, an active parent profile and onboarding_status='profile_pending'. Current Terms of Service and Privacy Policy versions are configured. | Q3: The verified parent enters or resumes parent-profile onboarding. | R3: 1. Load the existing parent profile and authenticated email. 2. Display email as read-only. 3. Parent selects or confirms the country calling code. 4. Parent enters a mobile number. 5. Parent may optionally enter a display name. 6. Parent accepts the current Terms and Privacy Policy. 7. Client and server validate the mobile number using country-aware rules. 8. Server stores the number in E.164 format and updates the existing profile. 9. Versioned policy acceptance records are written idempotently. 10. onboarding_status changes to learner_pending. 11. Continue directly to learner-profile creation. | S3: Invalid number: show country-aware validation feedback and retain entered values. Missing number: block submission. Display name omitted: allow submission and retain NULL. Profile already complete: redirect to the next incomplete onboarding step. Policy version changed: require acceptance of the current version. Save failure: preserve form state and allow retry. Expired session: return to login and resume the same step. Duplicate submission: update the existing profile and reuse consent records. Later number change: validate and audit; no OTP is required in Version 1. | T3: Authenticated email; optional display name; selected country/calling code; mandatory mobile number; accepted Terms version; accepted Privacy version; locale and timezone. | U3: Updated parent profile with phone_e164, optional display_name and onboarding_status='learner_pending'; consent records; audit event; invoice contact email and computed invoice recipient label. | V3: Display authenticated email as read-only. Show Parent name as optional. Show country/calling-code selector and mandatory Mobile number field. Explain that the number is format-validated but not SMS-verified. Provide inline country-aware validation. Show Terms and Privacy acceptance controls. Disable Continue until mandatory inputs are valid. Do not show address or date-of-birth fields. Preserve values and show Retry after a failed save. | W3: GET /v1/parent/profile returns authenticated email, profile fields, onboarding status and current policy versions. PATCH /v1/parent/profile accepts optional displayName, phoneCountryCode, mobileNumber, locale, timezone, acceptedTermsVersion and acceptedPrivacyVersion. The server validates and normalizes the number to E.164. It updates the profile, writes idempotent consent records and advances onboarding_status in one transaction. No endpoint sends or validates an SMS OTP in Version 1. invoiceRecipientLabel = non-empty trimmed display_name, otherwise authenticated email. | X3: profiles: - display_name text nullable - phone_e164 text nullable before onboarding; application-required after onboarding - phone_country_code text nullable - locale text not null default 'en-IN' - timezone text not null default 'Asia/Kolkata' - onboarding_status text consent_records: - id uuid primary key - parent_user_id uuid references profiles(id) - consent_type text - policy_version text - granted boolean - granted_at timestamptz - revoked_at timestamptz nullable - unique(parent_user_id, consent_type, policy_version) Do not add phone_verified_at, postal_address or parent_date_of_birth in Version 1. | Y3: Treat the mobile number as personal data. Return it only to the authenticated parent and authorized support/admin roles. Mask it in logs and support views. Do not use it for SMS, marketing or authentication without separate consent and requirements. Use a maintained phone-number parsing library rather than custom regular expressions alone. Email remains the invoice-delivery address and authentication identifier. Rate-limit profile updates. Store policy acceptance version and timestamp. | Z3: Profile load/update p95 under 1.5 seconds. Support international E.164-compatible numbers. Keyboard accessible and usable at 320px width. Profile and consent update must be transactional. No duplicate profile or consent records. Normalization is deterministic for the same valid input. | AA3: AC1 A verified parent with profile_pending is directed to onboarding. AC2 The existing profile is updated rather than duplicated. AC3 The parent cannot continue without a valid mobile number. AC4 A valid number is stored in E.164 format. AC5 No SMS OTP is sent or required. AC6 The parent can complete onboarding without a display name. AC7 Email is read-only and sourced from Supabase Auth. AC8 Terms and Privacy versions are recorded with timestamps. AC9 Completion advances onboarding_status to learner_pending. AC10 Postal address and parent date of birth are not requested or stored. AC11 Invoices are delivered to the authenticated email. AC12 Invoice label uses display name when present and email otherwise. AC13 Repeated submissions create no duplicate records. AC14 Failed saves preserve entered values and support retry. | AB3: IA-001; parent profile schema; consent schema; current Terms and Privacy versions; phone-number parsing library; learner-profile creation route; invoice template. | AC3: Uses brief progressive onboarding while deliberately limiting data collection. | AE3: Use a libphonenumber-compatible library for server validation and E.164 normalization. Do not enforce phone uniqueness. Keep phone_e164 nullable at database level because the profile exists before onboarding, but require it for learner_pending and complete states. Perform profile update, consent inserts and status transition transactionally. Do not create OTP UI, OTP tables, SMS integration or a verified-phone flag. Create one invoiceRecipientLabel utility returning display_name or authenticated email. Mask numbers in logs and administration screens. Exact build packet: 09_Codex_Build_Specs!CBS-IA-002 | AF3: AT-IA-002-01, AT-IA-002-02, AT-IA-002-03, AT-IA-002-04, AT-IA-002-05, AT-IA-002-06, AT-IA-002-07, AT-IA-002-08, AT-IA-002-09, AT-IA-002-10, AT-IA-002-11, AT-IA-002-12, AT-IA-002-13, AT-IA-002-14 | AG3: 1.0 | AH3: Product Owner | AI3: 2026-07-30
A4: IA-003 | B4: EP-IDENTITY-01 | C4: Identity & Access | D4: Account Security & Lifecycle | E4: Parent credential changes and soft account deletion | F4: Must Have | G4: Approved | H4: Yes | I4: Done | J4: Functional | K4: Babysteps Platform | L4: Parent | M4: As a parent, I want to safely change my password or login email and deactivate my account so that I can maintain control of my Babysteps identity without permanently deleting retained records. | N4: Babysteps shall allow an authenticated active parent to change the account password, request a login-email change and soft-delete the account. Email changes require current-password reauthentication and verification of the proposed new email. The verification link expires exactly 24 hours after issue. The current email remains active until verification succeeds. Immediately after successful verification, the new email becomes the authoritative login, invoice and receipt address, and the previous email is archived. Account deletion is a soft delete only: records remain in the database, all access is blocked and active sessions are revoked. Restoration is administrator-controlled and never self-service in Version 1. | O4: 1. Credential changes require an authenticated, verified and active parent profile. 2. The current password must be revalidated immediately before password change, email-change request or account soft deletion. 3. New passwords must meet the central policy, match confirmation and differ from the current password. 4. The new email must be normalized, valid, different from the current email and unused by another Auth identity. 5. Supabase Secure Email Change must be disabled so only the proposed new email requires verification. 6. Auth email-link expiry must be configured to 86,400 seconds. 7. While verification is pending, the current email remains the active login and invoice address. 8. On successful email verification, the new email activates immediately and the old email is archived. 9. Expired, cancelled or failed email changes leave the current email unchanged. 10. Only one pending email-change request may exist per parent. 11. Soft delete sets account_status='deleted', deleted_at and auth_revoked_before; it never physically deletes Auth, profile, learner, progress, consent, billing, invoice or audit records. 12. Soft deletion revokes all Babysteps parent, learner and app sessions. 13. Platform middleware denies deleted accounts even if a Supabase Auth session can still be established. 14. Deleted accounts cannot self-restore. An authorized platform administrator may restore the account, after which the parent must sign in again. 15. Every subscription belongs to its purchaser parent through purchaser_parent_id. Subscription cancellation and financial retention are governed by Billing; this requirement emits an account_soft_deleted event but does not silently delete financial records. | P4: IA-001 and IA-002 are implemented. The parent has a verified Supabase identity, an active profile and completed profile onboarding. Supabase email delivery and callback URLs are configured. | Q4: The parent opens Account Settings → Security, requests a password/email change, or confirms soft deletion. | R4: Password change: 1. Parent enters current password, new password and confirmation. 2. Server reauthenticates the current email/password using an isolated non-persistent Supabase client. 3. Server validates the new password. 4. Auth password is updated. 5. Success is shown and the action is audited. Email change: 1. Parent enters proposed email and current password. 2. Server reauthenticates and validates uniqueness/format. 3. A pending email-change record is created. 4. Supabase Auth updateUser({email:newEmail}) sends verification to the new email only. 5. Current email remains active. 6. Verification callback validates the Supabase email_change token within 24 hours. 7. Callback confirms the Auth user now has the new email. 8. Old email is inserted into parent_email_history and request is marked verified. 9. Sessions are refreshed; new email becomes login/invoice email immediately. 10. A reconciliation action completes archival if Auth changed but callback persistence was interrupted. Soft delete: 1. Parent reviews retained-data warning and enters current password plus DELETE confirmation. 2. Server reauthenticates. 3. In one platform transaction, set deleted status/timestamps, revoke platform sessions and write audit/outbox events. 4. Sign the browser out and show the deleted-account confirmation. 5. Subsequent platform access is denied. | S4: Wrong current password: reject and throttle without changing credentials. New password invalid or unchanged: show policy error. New email already used: reject without revealing unrelated account details. Verification link expired after 24 hours: current email remains active; allow a new request. Pending request replaced: cancel the old request before creating the new one. Verification callback replayed: return the already-completed result without duplicating email history. Auth email changed but archival write failed: reconciliation finalizes the pending request idempotently. Soft deletion with active sessions: revoke them all. Soft-deleted login: authenticate only at Supabase if applicable, then platform immediately denies and signs out. Restore request by parent: deny and direct to support. Admin restoration: reactivate profile but do not restore old sessions. | T4: Current password; new password and confirmation; proposed email; Supabase Auth user ID/current email; email-change token; typed deletion confirmation; optional deletion reason. | U4: Updated Auth password or email; archived prior email; email-change request status; soft-deleted/restored profile status; revoked sessions; audit and outbox events; refreshed invoice-delivery email. | V4: Account Settings → Security must show current verified email and actions for Change password, Change email and Delete account. Password form requires current/new/confirm fields and show/hide controls. Email-change form explains that the old email remains active until verification and that the link expires in 24 hours. Pending-email state shows proposed address, expiry time, Resend and Cancel. Delete flow uses a high-friction confirmation screen, retained-data explanation, current password and exact DELETE text. Deleted accounts see no normal dashboard. All screens are keyboard accessible, responsive at 320px and preserve non-sensitive inputs on retry. | W4: GET /v1/account/security POST /v1/account/password/change POST /v1/account/email-change/request POST /v1/account/email-change/resend POST /v1/account/email-change/cancel GET /auth/email-change/callback POST /v1/account/soft-delete POST /v1/admin/accounts/{parentId}/restore Use Supabase signInWithPassword for immediate current-password reauthentication. Use updateUser({email}) with Secure Email Change disabled and email OTP expiry 86400. The callback verifies type='email_change', completes archive/history state and refreshes the session. Every write endpoint is idempotent or protected by request/state constraints. | X4: profiles additions: - deleted_at timestamptz null - deleted_by_user_id uuid null - auth_revoked_before timestamptz null email_change_requests: - id uuid primary key - parent_user_id uuid not null references profiles(id) - old_email text not null - new_email text not null - status text not null: pending, verified, expired, cancelled - requested_at timestamptz not null - expires_at timestamptz not null - verified_at timestamptz null - cancelled_at timestamptz null - supabase_request_nonce text null - unique partial index: one pending request per parent parent_email_history: - id uuid primary key - parent_user_id uuid not null references profiles(id) - email text not null - archived_at timestamptz not null - reason text not null default 'email_changed' Use existing platform session tables/outbox/audit tables. Do not physically delete rows. | Y4: Passwords and verification tokens must never be logged or stored. Current-password reauthentication uses an isolated no-persist client and discards the password immediately. Email-change callbacks validate redirect origin, token type, request ownership and expiry. Old and new emails are personal data; mask them in general logs. Soft-delete endpoint is CSRF-protected, rate-limited and requires current password plus exact confirmation. All protected middleware checks account_status and auth_revoked_before. Admin restoration requires platform_admin authorization and a mandatory reason. Archive records and audit events are append-only. | Z4: Security settings load p95 under 1.5 seconds. Credential-change request p95 under 2 seconds excluding email delivery. Email-change expiry is exactly 24 hours based on server timestamps. No duplicate pending request or archived-email row from callback replay. Soft-delete access denial becomes effective on the next platform request. All sensitive screens meet WCAG keyboard/focus requirements. | AA4: AC1 Active parent can view current verified login email. AC2 Current password is required for password change, email change and soft delete. AC3 Successful password change invalidates the old password. AC4 New email remains inactive until verification. AC5 Email-change verification expires after 24 hours. AC6 Successful verification immediately activates the new email. AC7 Old email is archived exactly once after activation. AC8 Expired/cancelled request leaves old email active. AC9 Invoice and receipt delivery uses the newly verified email. AC10 Soft deletion retains all database records. AC11 Soft deletion revokes platform/app sessions and blocks access. AC12 Deleted accounts cannot self-restore. AC13 Authorized admin can restore status but not sessions. AC14 Replayed requests/callbacks remain idempotent. AC15 Passwords and verification tokens never appear in logs or platform tables. | AB4: IA-001; IA-002; Supabase email auth settings; platform session revocation; audit/outbox infrastructure; Billing integration event; administrator authorization. | AC4: Not a gamification feature; it is a required account-control and trust foundation. | AD4: https://supabase.com/docs/reference/javascript/auth-updateuser https://supabase.com/docs/reference/javascript/auth-resend https://supabase.com/docs/guides/local-development/cli/config | AE4: Configure Supabase Auth with secure email change disabled and email link/OTP expiry 86400 seconds. Use a pending-request table even though Supabase sends the email so the product can show state, expiry, cancel/resend and archive the old email. Make callback completion and reconciliation idempotent. Use profile account_status plus auth_revoked_before as the authoritative platform access gate. Do not call auth.admin.deleteUser. Soft-delete transaction must revoke all Babysteps session records and emit account_soft_deleted. Admin restoration must require a reason and create a fresh login requirement. Exact build packet: CBS-IA-003 | AF4: AT-IA-003-01 through AT-IA-003-15 | AG4: 1.0 | AH4: Product Owner | AI4: 2026-07-30
A5: IA-004 | B5: EP-IDENTITY-01 | C5: Identity & Access | D5: Child Passkey Access | E5: Windows Hello and Apple passkey access for learners | F5: Nice to Have | G5: Approved | H5: Yes | I5: Backlog | J5: Functional | K5: Shared Contract | L5: Parent and Learner | M5: As a parent, I want to enroll a learner for passkey access on compatible Windows and Mac devices so that the child can enter Babysteps without using the parent's email and password. | N5: Babysteps may provide optional learner access using standards-based WebAuthn passkeys backed by the operating system platform authenticator. On Windows, the local verification experience may be Windows Hello PIN, face or fingerprint. On macOS, it may be Touch ID, device passcode or another Apple passkey flow. Babysteps shall never receive or store the operating-system PIN or biometric. A parent must authenticate and enroll the learner first. A successful passkey assertion creates only a restricted learner session and never grants parent, billing or administrative access. | O5: 1. This feature is Nice to Have and must not block Version 1 launch. 2. Use WebAuthn/passkeys, not a Babysteps-owned Windows or Mac PIN. 3. Enrollment requires an active verified parent, completed onboarding and recent current-password reauthentication. 4. The selected learner must be owned by the parent or explicitly shared with that parent through learner-level authorization, and must be active. 5. Registration and authentication occur only on the central account origin. 6. Production RP ID is account.babysteps.in; production origin is https://account.babysteps.in. Local/preview environments use separately configured valid RP IDs/origins. 7. Registration requests authenticatorAttachment='platform', residentKey='required', userVerification='required' and attestation='none'. 8. Server challenges are random, single-use and expire after five minutes. 9. Store only WebAuthn credential material and metadata; never store PINs, biometric templates or platform secrets. 10. One learner may have multiple active passkeys; every credential can be individually named and revoked by an authorized parent. 11. Successful authentication creates a learner-only session scoped to the selected learner. 12. Learner passkey sessions cannot access parent account settings, billing, learner-management administration or another learner. 13. The one-active-learner-session rule still applies. 14. If passkeys are unavailable, cancelled or fail, fallback is parent email/password login; do not create a custom child PIN here. 15. Apple passkeys may synchronize through iCloud Keychain; do not promise that a credential is restricted to one physical Mac. 16. Signature-counter anomalies are evaluated according to passkey behavior; zero/non-incrementing counters for synced passkeys are logged rather than automatically treated as cloning. | P5: IA-001 through IA-003, learner profiles, learner authorization, app-launch/session control and WebAuthn-capable HTTPS origins are implemented. | Q5: An authenticated parent enrolls a learner, or an enrolled learner selects Use passkey. | R5: Enrollment: 1. Parent signs in and reauthenticates with current password. 2. Parent selects an active learner they own or are authorized to manage. 3. Parent gives the credential a friendly label. 4. Server creates one-time registration options and stores a challenge. 5. Browser calls navigator.credentials.create through a WebAuthn library. 6. Windows Hello or Apple platform authenticator performs local user verification. 7. Server verifies challenge, origin, RP ID hash, attestation response and user-verification flag. 8. Store credential ID, public key, counter and metadata. 9. Show enrolled credential and revocation controls. Learner authentication: 1. Open central Child access screen. 2. Select learner profile. 3. Server creates authentication options limited to that learner's non-revoked credentials. 4. Browser calls navigator.credentials.get. 5. Platform authenticator performs local verification. 6. Server verifies challenge, origin, RP ID, signature, credential ownership and UV flag. 7. Update counter/last-used metadata. 8. Create or refresh only a restricted learner authentication session. 9. Continue to the unified launcher. LP-004 independently authorizes learning-session start and must never revoke or replace an ongoing learning session. | S5: Unsupported browser/platform: hide or disable enrollment and explain fallback. User cancels OS prompt: return to learner selection without creating a session. Challenge expired/used: issue a fresh challenge. Unknown/revoked credential: deny. Credential belongs to another learner: deny and audit. Origin/RP mismatch or signature failure: deny and security-log. Counter anomaly: apply passkey-aware policy and log; do not incorrectly reject synced credentials solely for zero counter. Parent account is suspended or soft deleted: deny passkey use and revoke related authentication sessions. Lost device: parent revokes the credential from account settings. No enrolled credential: require parent login. Multiple matching credentials: allow the browser/platform chooser. | T5: Parent session and password reauthentication; learner ID; credential friendly label; WebAuthn registration/response objects; authentication assertion; server challenge; configured RP ID/origin. | U5: Stored learner passkey credential; registration/authentication audit events; restricted learner authentication session; updated credential usage metadata; revocation state. | V5: Add parent-facing Learner access settings with Enroll passkey and credential list/revoke controls. Add a central Child access page with learner selection and Use passkey. Use neutral wording such as 'Use device passkey'; platform-specific helper text may say Windows Hello or Touch ID when detected. Never ask for or display a Babysteps PIN field. Show compatibility/fallback messaging. Warn parents that Apple passkeys may sync across their Apple devices. Ensure keyboard accessibility, clear focus, cancel handling and 320px responsive behavior. | W5: POST /v1/learner-passkeys/registration/options POST /v1/learner-passkeys/registration/verify POST /v1/learner-passkeys/authentication/options POST /v1/learner-passkeys/authentication/verify GET /v1/learner-passkeys?learnerId= DELETE /v1/learner-passkeys/{credentialId} Use @simplewebauthn/server and @simplewebauthn/browser or an equivalent standards-conformant, locked dependency. Registration and verification are server-side authoritative. Successful authentication creates only a restricted learner authentication session rather than a parent Supabase Auth session. Starting a learning session is a separate LP-004 operation and cannot replace an ongoing session. | X5: learner_passkey_credentials: - id uuid primary key - learner_id uuid not null - created_by_parent_user_id uuid not null - credential_id text/base64url not null unique - public_key text/base64url not null - sign_count bigint not null default 0 - transports jsonb null - aaguid text null - backup_eligible boolean null - backup_state boolean null - friendly_name text not null - created_at timestamptz not null - last_used_at timestamptz null - revoked_at timestamptz null - revoked_by_parent_user_id uuid null webauthn_challenges: - id uuid primary key - purpose text: register or authenticate - parent_user_id uuid null - learner_id uuid not null - challenge_hash text not null - expires_at timestamptz not null - used_at timestamptz null - created_at timestamptz not null Add indexes on learner active credentials and challenge expiry. | Y5: Use HTTPS outside localhost. Validate challenge, origin, RP ID hash, signature, credential ownership and userVerification=true. Attestation preference is none. Store no operating-system PIN or biometric data. Challenges are hashed, single-use and five-minute expiry. Enrollment requires recent parent-password reauthentication and CSRF protection. Learner session permissions are least privilege. Credential lists reveal only friendly label and safe metadata. Rate-limit options/verification endpoints. Deny credential use when the owning parent account is suspended or soft deleted, or when the credential itself is revoked. Audit suspicious assertions without logging raw credential responses unnecessarily. | Z5: Passkey options endpoints p95 under 1 second. Verification p95 under 1.5 seconds excluding OS UI time. Support current WebAuthn-capable browsers on Windows and macOS as an optional compatibility target. No launch dependency if unsupported. Credential verification is deterministic and covered by contract tests. Accessibility and fallback flows remain usable without passkeys. | AA5: AC1 Only an authenticated reauthenticated parent can enroll. AC2 Parent can enroll a passkey for an owned active learner. AC3 Windows Hello-compatible platform authenticator can complete WebAuthn registration/authentication. AC4 macOS Apple passkey/Touch ID-compatible platform authenticator can complete WebAuthn registration/authentication. AC5 Babysteps never receives or stores PIN/biometric data. AC6 Authentication requires user verification. AC7 Credential cannot authenticate another learner. AC8 Successful assertion creates only a restricted learner authentication session and does not start or replace a learning session. AC9 Parent/billing/admin routes are denied to learner session. AC10 Challenge replay/expiry is rejected. AC11 Parent can list, label and revoke each credential. AC12 Revoked credential cannot authenticate. AC13 Unsupported/cancelled flow falls back to parent login. AC14 Synced Apple passkeys are not falsely described as one-Mac-only. AC15 Feature absence does not block Version 1 core flows. | AB5: IA-001 to IA-003; learner-profile requirements; active learner-session control; unified launcher; HTTPS/custom domain; WebAuthn library; browser compatibility testing. | AC5: Comparable to frictionless re-entry in learning apps, but implemented as a secure optional device capability rather than a proprietary child PIN. | AD5: https://learn.microsoft.com/en-us/windows/apps/develop/security/implement https://developer.apple.com/passkeys/ https://developer.apple.com/documentation/authenticationservices/supporting-passkeys | AE5: Implement one cross-platform WebAuthn passkey feature rather than separate Windows and Mac authentication systems. Use the central account origin and a configured RP ID. Require platform authenticator and user verification. Do not call the feature a Windows PIN in the data/API model. Create restricted learner sessions only. Keep all passkey code feature-flagged and optional. Test Windows Hello and macOS Safari/Chrome manually in addition to automated WebAuthn fixtures. Exact build packet: CBS-IA-004 | AF5: AT-IA-004-01 through AT-IA-004-15 | AG5: 1.0 | AH5: Product Owner | AI5: 2026-07-30
A6: HH-001 | B6: EP-HOUSEHOLD-FUTURE | C6: Deferred Architecture | D6: Household Entity | E6: Separate household entity and membership boundary | F6: Nice to Have | G6: Deferred | H6: No | I6: Deferred | J6: Functional | K6: Babysteps Platform | L6: Parent and Platform Administrator | M6: As a future platform operator, I may need a shared family entity that exists independently of any one parent so multiple adults and shared services can be managed under one stable boundary. | N6: In a future release, Babysteps may introduce a separate household entity with household membership records. Version 1 shall not create, read, require or expose a household entity. Parent profile UUIDs remain the direct ownership root for learners and subscriptions until this requirement is reactivated. | O6: Deferred scope includes: 1. households table and stable household_id. 2. household_members table. 3. owner/member/viewer membership roles. 4. automatic or explicit household creation. 5. household status and lifecycle. 6. parent membership in one or more households. 7. migration of existing parent-owned learners into a household. 8. household-level authorization and audit rules. Version 1 rules: - Do not create household tables. - Do not add household_id to learners, subscriptions, entitlements, passkeys or progress. - Do not show household onboarding. - Do not make current features depend on this deferred concept. | P6: A proven future need exists for a shared family entity that cannot be represented safely by direct parent ownership and learner-level permissions. | Q6: A formal architecture decision reactivates the deferred household epic. | R6: No Version 1 flow. Future design must include migration of existing parent-owned records without breaking stable learner IDs, subscription history or access controls. | S6: Until reactivated, requests for household creation or membership return no route because the feature does not exist. Future migration must define duplicate-family resolution, ownership conflicts and rollback. | T6: Future household name/status; membership invitations; existing parent, learner and subscription ownership records. | U6: Future household record and membership relationships. | V6: No Version 1 UI. A future release may add Family settings only after the underlying ownership and migration model is approved. | W6: No Version 1 API. Future API surface must be separately specified and versioned. | X6: No Version 1 tables or columns. Future implementation must include an explicit migration plan from owner_parent_id and purchaser_parent_id. | Y6: Do not infer family relationships from email domains, phone numbers, surnames or shared devices. Future membership must be explicit and audited. | Z6: Must not add query joins or latency to Version 1 while deferred. Future migration must preserve current IDs and data integrity. | AA6: AC1 No household table or household_id exists in Version 1. AC2 Learners remain keyed by owner_parent_id. AC3 Subscriptions remain keyed by purchaser_parent_id. AC4 Deferred scope does not affect current onboarding or launch. | AB6: Direct parent ownership architecture; learner ownership; purchaser-parent subscription model. | AC6: None; deferred architecture only. | AE6: Do not implement. Keep this row for future product/architecture review. Reactivation requires a new decision, versioned requirement and complete Codex build packet. | AG6: 0.1-deferred | AH6: Product Owner | AI6: 2026-07-30
A7: HH-002 | B7: EP-HOUSEHOLD-FUTURE | C7: Deferred Architecture | D7: Household Roles | E7: Household-wide guardian roles and ownership transfer | F7: Nice to Have | G7: Deferred | H7: No | I7: Deferred | J7: Functional | K7: Babysteps Platform | L7: Parent, Guardian and Platform Administrator | M7: As a future family administrator, I may want multiple adults to share authority over an entire family group and transfer household ownership. | N7: Household-wide adult membership, owner roles, ownership transfer and family-wide permissions are deferred. Version 1 may later support explicit learner-level guardian access, but that must not imply or create a household-wide role. | O7: Deferred scope includes: 1. inviting an adult to the whole household. 2. household owner, guardian and viewer roles. 3. ownership transfer. 4. final-owner protection. 5. whole-family access revocation. 6. household-wide reporting permissions. 7. adult membership across multiple households. Version 1: - Additional-adult access, if approved, is granted per learner. - A guardian cannot automatically see every learner owned by another parent. - No household owner role exists. | P7: A future use case requires the same adult permissions to apply automatically to every current and future learner in a shared family entity. | Q7: The household entity requirement is reactivated and a role/permission matrix is approved. | R7: No Version 1 household invitation or ownership-transfer flow. | S7: Future flows must handle expired invitations, duplicate accounts, final-owner protection, conflicting ownership and access removal. | T7: Future invitee email; membership role; household ID; ownership-transfer confirmation. | U7: Future household membership and authorization records. | V7: No Version 1 household-member UI. Learner-level sharing remains a separate requirement. | W7: No Version 1 household membership APIs. | X7: No household_members or household_invites tables in Version 1. | Y7: Future roles must use least privilege, explicit consent, auditable invitations and cross-family isolation. | Z7: No Version 1 runtime dependency. Future role checks must remain centrally testable and deterministic. | AA7: AC1 No household-wide role exists in Version 1. AC2 Learner-level sharing does not grant implicit access to other learners. AC3 Ownership transfer is unavailable until reactivated. | AB7: HH-001 deferred household entity; future learner guardian requirements. | AC7: None; deferred collaboration model. | AE7: Do not implement. Any future activation requires exact role definitions, invitation expiry, ownership-transfer rules, authorization matrix and Codex packet. | AG7: 0.1-deferred | AH7: Product Owner | AI7: 2026-07-30
A8: HH-003 | B8: EP-HOUSEHOLD-FUTURE | C8: Deferred Architecture | D8: Household Billing | E8: Household-owned subscriptions and shared family billing | F8: Nice to Have | G8: Deferred | H8: No | I8: Deferred | J8: Functional | K8: Babysteps Platform | L8: Paying Parent and Platform Administrator | M8: As a future family account, I may want one jointly owned subscription and billing relationship that is independent of the individual purchaser. | N8: Household-owned subscriptions, shared family billing ownership and transfer of the commercial counterparty are deferred. In Version 1, every subscription belongs to the paying parent through purchaser_parent_id, is assigned to exactly one learner through assigned_learner_id, and may represent either one app or a bundle of apps. | O8: Deferred scope includes: 1. household_id as subscription owner. 2. multiple billing administrators. 3. transfer of billing ownership between adults. 4. household-level payment methods. 5. shared invoice access. 6. family-wide plan administration independent of purchaser. 7. migration from purchaser_parent_id to household ownership. Version 1: - purchaser_parent_id and assigned_learner_id are mandatory. - The paying parent is the commercial counterparty. - Individual-app and bundle entitlements apply only to the subscription's assigned learner without changing commercial ownership. - Additional guardians receive no billing access unless separately and explicitly approved. | P8: A future commercial model requires joint family ownership or transfer of subscriptions without keeping the purchaser as the legal/account owner. | Q8: Billing strategy approves household ownership and the household entity is reactivated. | R8: No Version 1 household billing flow. | S8: Future design must handle payment-method ownership, invoice access, refunds, tax identity, ownership transfer and disputes. | T8: Future household ID; billing-administrator roles; subscription/payment records. | U8: Future household-owned subscription and billing authority. | V8: No household billing UI in Version 1. | W8: No household-owned billing API in Version 1. | X8: Subscriptions continue to use purchaser_parent_id and assigned_learner_id; do not add household_id. Product definitions determine whether the subscription grants one app or a bundle of apps. | Y8: Billing access is restricted to the purchaser parent and authorized platform support. Financial records remain auditable and retained. | Z8: No Version 1 impact. Future migration must preserve invoice, payment, refund and entitlement history. | AA8: AC1 Every Version 1 subscription has purchaser_parent_id and assigned_learner_id. AC2 One subscription covers exactly one learner. AC3 No household_id exists on subscriptions. AC4 Individual-app subscriptions grant one app; bundle subscriptions grant all included apps to the assigned learner. AC5 Invoices remain associated with the paying parent's verified email. | AB8: Future household entity; billing and subscription requirements. | AC8: None; deferred commercial model. | AE8: Do not implement. Future activation requires legal/commercial ownership rules, billing authorization, migration design and a complete Codex packet. The active Version 1 rule remains one purchaser-parent subscription assigned to one learner. | AG8: 0.1-deferred | AH8: Product Owner | AI8: 2026-07-30
A9: LP-001 | B9: EP-LEARNER-01 | C9: Learner Profiles | D9: Learner Creation | E9: Learner profile creation and direct parent ownership | F9: Must Have | G9: Approved | H9: Yes | I9: Done | J9: Functional | K9: Babysteps Platform | L9: Parent | M9: As a verified parent, I want to create a learner profile for any person—including myself—with a unique familiar name and date of birth so that every Babysteps app can identify the learner consistently and tailor presentation appropriately. | N9: Babysteps shall allow an authenticated, verified and active parent to create one or more learner profiles for children, adults or the parent themselves. Every learner shall receive a permanent UUID and exactly one owner_parent_id derived from the authenticated parent profile. Display name and date of birth are mandatory; an approved platform avatar is optional. Learner display names must be unique across every learner permanently owned by the parent. There is no maximum learner age and learner creation must not be rejected because the learner is an adult. The learner profile shall not receive a separate email, password, phone number or Supabase Auth identity. Learner creation is independent of subscriptions, entitlements and app progress. | O9: 1. owner_parent_id comes only from the authenticated server session and is never accepted from the client. 2. A parent may own multiple learners and may create a learner profile for themselves. 3. Every learner has exactly one primary owner. A self-learner profile is still a separate learner record owned by the same parent profile. 4. Display name is mandatory, 1–50 visible characters and stored using the parent's preferred capitalization. 5. Before uniqueness comparison, normalize with Unicode NFKC, trim leading/trailing whitespace, collapse internal whitespace runs to one space and apply locale-independent case folding. 6. unique(owner_parent_id, normalized_display_name) applies across every learner permanently owned by the parent. Learner records are not paused, archived, hidden or deleted in Version 1. 7. Date of birth is mandatory, stored as a PostgreSQL date and must be a valid non-future date. 8. There is no maximum learner age. Learner creation accepts any valid past date of birth supported by the database. Age must not be used as an eligibility gate. 9. Do not persist a separate age field. Calculate ageYears and ageMonths from date_of_birth and an explicit ageAsOfDate. 10. Raw date of birth is visible only to the owning parent, authorized support/admin roles and trusted platform services. Learning apps receive derived ageYears, ageMonths and ageAsOfDate by default, not raw date of birth. 11. Age may tailor vocabulary, explanation length, visual density, scaffolding, narration and delivery speed. Age must never override prerequisites, demonstrated mastery, remediation or advancement. 12. Avatar is optional and must reference an active approved platform avatar. Learner photo upload is excluded. 13. The learner record has no lifecycle status field. 14. The first successful learner creation changes parent onboarding_status from learner_pending to complete in the same transaction. 15. Learner creation succeeds without any subscription. No subscription, entitlement, session allowance or app-progress row is created. 16. The create operation requires a parent-scoped idempotency key. Repeating an already successful request returns the same learner. 17. When the owning parent is suspended or soft deleted, all access to owned learner profiles—including a self-learner profile—is denied. Learner records remain retained. 18. A restored parent must establish a new login session before learner access resumes. 19. Additional guardians, when implemented, receive explicit learner-level permissions and do not replace owner_parent_id automatically. 20. No separate relationship or household field is required to indicate that a learner is the parent; the direct owner relationship and learner record remain sufficient for Version 1. | P9: IA-001 through IA-003 are implemented. The parent has a verified active Supabase session, profile onboarding is complete through learner_pending, and the approved-avatar registry is available. | Q9: The parent selects Add learner during onboarding or from Account → Learners. | R9: 1. Load the learner-creation form and approved avatar choices. 2. Parent enters the learner's display name and date of birth. The learner may be the parent. 3. Parent may choose an avatar. 4. Client performs preliminary validation. 5. Client submits displayName, dateOfBirth, optional avatarId and idempotencyKey. 6. Server authenticates the parent and requires verified, active account status. 7. Server rejects all unknown ownership fields. 8. Server normalizes the name and checks parent-scoped uniqueness. 9. Server validates that date of birth is a real, non-future calendar date. It does not enforce a maximum learner age. 10. Server validates the avatar. 11. In one transaction, create the learner, record the idempotency result and audit event, and set onboarding_status='complete' when this is the first learner. 12. Return the learner plus derived ageYears, ageMonths and ageAsOfDate. 13. Show Add another learner and Continue actions. | S9: Missing/invalid name: reject and retain entered values. Duplicate normalized name: return LEARNER_NAME_ALREADY_EXISTS and identify no other learner details. Missing/invalid/future date of birth: reject with a specific validation code. Adult or elderly learner date of birth: accept when it is a valid past date. Unusually old but valid date: allow creation; the UI may request confirmation without enforcing an age ceiling. Unknown avatar: reject. Client sends ownerParentId or householdId: reject as FORBIDDEN_FIELD and audit. Expired session or unverified email: require authentication/verification. Suspended or soft-deleted parent: return ACCOUNT_NOT_ACTIVE or ACCOUNT_DELETED before returning learner data. Duplicate idempotency key with same payload: return original learner. Duplicate idempotency key with different payload: return IDEMPOTENCY_KEY_REUSED. Transaction failure: roll back learner, onboarding, idempotency completion and audit/outbox state. No subscription: create learner normally. Concurrent same-name requests: database uniqueness constraint permits only one. | T9: displayName; dateOfBirth in YYYY-MM-DD; optional avatarId; required idempotencyKey. Authenticated parent identity, parent timezone, approved avatar registry and shared age-policy configuration are server inputs. | U9: Permanent learner UUID; owner relationship; stored display and normalized name; date of birth; derived age context; optional avatar; onboarding status; idempotency result; audit event. | V9: Routes: - /onboarding/learners/new - /account/learners/new Screen: - Heading Add a learner. - Required Display name field with helper text: Use the name or nickname this learner should see in Babysteps. - Required Date of birth control with accessible day/month/year entry and calendar support. - Optional approved-avatar picker. - Privacy message explaining that age helps tailor presentation and pacing. - Explicit note that learners may be children or adults, including the account owner. - Create learner primary action. - After success: Continue and Add another learner. - Do not show separate learner email, phone, password, school, gender, legal-name or photo-upload fields. - Show duplicate-name and date errors inline. - Responsive at 320px; fully keyboard accessible; preserve non-sensitive input after retryable failure. | W9: POST /v1/learners Request: {displayName, dateOfBirth, avatarId?, idempotencyKey} Reject additional fields with a strict schema. Response: {learner:{id,displayName,dateOfBirth,ageYears,ageMonths,ageAsOfDate,avatarId,version}, onboardingStatus} GET /v1/learners Return only learners owned by or explicitly shared with the authenticated parent. For LP-001, ownership is the implemented path. GET /v1/learner-context/{learnerId} For authorized platform/app launch services, return {learnerId,displayName,avatarId,ageYears,ageMonths,ageAsOfDate,locale,timezone}. Raw dateOfBirth is excluded by default. All endpoints first enforce parent account status. Soft-deleted parents receive ACCOUNT_DELETED with no learner payload. | X9: learners: - id uuid primary key default gen_random_uuid() - owner_parent_id uuid not null references profiles(id) - display_name text not null - normalized_display_name text not null - date_of_birth date not null - avatar_id text null references approved_avatars(id) - version integer not null default 1 - locale text not null - timezone text not null - created_at timestamptz not null default now() - updated_at timestamptz not null default now() - unique(owner_parent_id, normalized_display_name) learner_creation_requests: - parent_user_id uuid not null - idempotency_key uuid not null - request_hash text not null - learner_id uuid null - status text not null check in ('processing','completed','failed') - created_at, completed_at - primary key(parent_user_id,idempotency_key) No household_id, subscription_id, child auth fields or persisted age column. | Y9: Learner ownership is derived from the authenticated session. Apply RLS/server authorization so unrelated parents cannot read or modify learners. Do not log raw date of birth or display name in infrastructure logs. Audit using parent ID, learner ID and event type; avoid duplicating raw learner data. Return raw date of birth only to the owning parent and specifically authorized support/admin views. Learning-app context exposes derived age only by default. Rate-limit learner creation. Reject mass assignment and unknown fields. Soft-deleted/suspended parent status is checked before every learner read/write and before passkey or app launch. No separate learner Supabase Auth identity is created. Date of birth must not be used for advertising or unrelated profiling. Adult and self-learner profiles receive the same authorization and privacy protections as all other learner profiles. | Z9: Create/list p95 under 1.5 seconds excluding transient provider latency. Concurrent duplicate-name creation remains consistent through the database unique constraint. Age calculation is deterministic for parent timezone and explicit as-of date. International Unicode names are supported. Learner creation has no maximum-age eligibility check. All learner-creation UI meets WCAG keyboard, label, focus and error requirements. No learner, onboarding or idempotency partial state after failure. | AA9: AC1 Verified active parent can create a learner. AC2 The parent may create a learner profile for themselves. AC3 Learner receives a permanent UUID. AC4 owner_parent_id is derived from the session. AC5 Client ownership fields are rejected. AC6 Display name and date of birth are mandatory. AC7 Name uniqueness is case-insensitive, Unicode-normalized and whitespace-normalized per parent. AC8 Learner records have no pause, archive, hide or delete lifecycle. AC9 Same normalized name is allowed for unrelated parents. AC10 Invalid and future birth dates are rejected. AC11 There is no maximum learner age and adult learners are accepted. AC12 Age is derived, not stored. AC13 Apps receive derived age context by default. AC14 Age adapts presentation but never overrides mastery. AC15 Avatar is optional and approved-list only. AC16 No separate learner email, phone, password, legal name, school, gender or household is collected. AC17 Learner creation requires no subscription. AC18 No subscription, entitlement, progress or session record is auto-created. AC19 First learner completes parent onboarding atomically. AC20 Idempotent retry returns one learner; conflicting key reuse is rejected. AC21 Concurrent duplicate names create one learner only. AC22 Soft-deleted parent cannot list, view, create or manage learners, including a self-learner profile. AC23 Soft deletion revokes app/passkey paths and returns no learner payload. AC24 Restored parent requires a new login session. AC25 Unrelated parents cannot access the learner. AC26 Raw DOB is absent from routine logs and default app context. | AB9: IA-001; IA-002; IA-003; approved avatar registry; learner authorization; future subscription/entitlement contracts; audit/idempotency infrastructure. | AC9: Profile creation is intentionally brief and child-friendly; unlike generic engagement systems, age only adjusts delivery while mastery remains authoritative. | AE9: Implement the learner table, name-normalization utility, DOB/age derivation, strict create/list/context APIs, onboarding transaction, RLS/server authorization, approved-avatar validation and parent-scoped idempotency. Use Unicode NFKC + whitespace collapse + locale-independent case folding for normalized_display_name. Accept any valid non-future date of birth. Do not implement a maximum learner age or age-based learner eligibility gate. Support a parent creating and using a learner profile for themselves without adding a special relationship table or separate Auth identity. Do not expose raw DOB to learning apps by default. Check parent account_status before every learner operation. Do not create household, subscription, entitlement, progress, session or learner Auth records. Exact build packet: CBS-LP-001 | AF9: AT-LP-001-01 through AT-LP-001-26 | AG9: 1.0 | AH9: Product Owner | AI9: 2026-07-30
A10: LP-002 | B10: EP-LEARNER-01 | C10: Learner Profiles | D10: Profile Correction | E10: Learner profile correction | F10: Must Have | G10: Approved | H10: Yes | I10: Done | J10: Functional | K10: Babysteps Platform | L10: Parent | M10: As the owning parent, I want to correct a learner's display name, date of birth or avatar without changing the learner's identity, access history or learning progress. | N10: Babysteps shall allow the authenticated owning parent to correct an existing learner profile's display name, date of birth and approved avatar. Corrections shall preserve the learner UUID, owner_parent_id, subscriptions, entitlements, progress, mastery, placement, session history and weekly usage. Learner profiles are permanent identities and Version 1 shall provide no pause, archive, restore, hide, merge, transfer or delete operation. | O10: 1. Only display_name, date_of_birth and avatar_id are editable. 2. learner.id, owner_parent_id, created_at, progress, mastery, subscription assignment, entitlement state and weekly session usage are immutable through this requirement. 3. Name corrections use the exact LP-001 normalization and parent-scoped uniqueness rules. 4. A capitalization or display-format correction is allowed when the normalized name remains owned by the same learner. 5. A name matching another learner owned by the parent is rejected. 6. Date of birth must be a valid, non-future PostgreSQL date. There is no maximum learner age. 7. Correcting date of birth recalculates derived age context for future sessions but never resets placement, mastery, completed work, progress or weekly usage. 8. An app session already in progress retains its learner-context snapshot; revised age context applies from the next app launch/session. 9. avatar_id may be changed to another active approved avatar or set to null. Learner photo upload remains excluded. 10. Each learners row has version integer not null default 1. 11. Every mutation requires expectedVersion and a parent+learner-scoped idempotencyKey. 12. A successful material correction increments version exactly once. 13. An exact no-op returns the current learner without incrementing version or writing a change event. 14. Same idempotency key and same payload returns the original completed result; same key with a different payload returns IDEMPOTENCY_KEY_REUSED. 15. Concurrent stale updates return LEARNER_VERSION_CONFLICT and never overwrite newer data. 16. A successful correction writes one learner_profile_changed event containing learner ID, actor parent ID, changed field names, previous version, new version and timestamp. Routine audit events do not duplicate raw DOB or display-name values. 17. Suspended or soft-deleted parent accounts cannot read or correct any learner profile. 18. Learner correction does not create, cancel, reassign or modify subscriptions or entitlements. 19. There is no parent-facing or admin-facing learner deletion path in LP-002. 20. All corrections are transactional and strict-schema validated; protected or unknown fields are rejected. | P10: LP-001 is implemented. The learner exists and is permanently owned by an active, verified parent account. | Q10: The owning parent selects Edit profile from the learner card or learner settings screen. | R10: 1. Load the current learner profile and version. 2. Parent edits display name, date of birth and/or avatar. 3. Client validates visible fields and submits only changed editable fields plus expectedVersion and idempotencyKey. 4. Server authenticates the parent and checks active account status. 5. Server verifies direct ownership before returning or mutating learner data. 6. Server strictly rejects protected and unknown fields. 7. Server validates name normalization/uniqueness, DOB and approved avatar. 8. Server obtains the idempotency record and locks the learner row. 9. If expectedVersion is stale, return LEARNER_VERSION_CONFLICT. 10. If the cleaned values are an exact no-op, return the current learner without a version increment. 11. Otherwise update supplied fields, increment version, update updated_at and write the change event atomically. 12. Return the updated learner and recalculated age context. 13. UI confirms Profile updated and refreshes the learner card. | S10: Duplicate normalized name: LEARNER_NAME_ALREADY_EXISTS. Missing, invalid or future date: DATE_OF_BIRTH_INVALID. Unknown/inactive avatar: AVATAR_NOT_AVAILABLE. No editable field supplied: NO_CHANGES_SUBMITTED. Exact cleaned no-op: return current learner successfully without mutation. Protected or unknown field: FORBIDDEN_FIELD and audit the attempted mass assignment. Stale expectedVersion: LEARNER_VERSION_CONFLICT with no changed data. Same idempotency key and payload: return original result. Same idempotency key with different payload: IDEMPOTENCY_KEY_REUSED. Unrelated parent: LEARNER_NOT_FOUND without existence disclosure. Suspended/deleted owner: ACCOUNT_SUSPENDED or ACCOUNT_DELETED before learner payload. Transaction failure: roll back profile, version, idempotency completion and change event. Correction during active app session: existing session continues with its original context snapshot; new context applies later. | T10: learnerId path parameter; optional displayName; optional dateOfBirth YYYY-MM-DD; optional avatarId including null; required expectedVersion; required idempotencyKey. At least one editable field must be supplied. | U10: Updated permanent learner profile; incremented version when materially changed; derived ageYears, ageMonths and ageAsOfDate; change event; idempotency result. No subscription, entitlement, progress or session changes. | V10: Route: /account/learners/{learnerId}/edit Screen: - Heading Edit learner profile. - Current display name, DOB and avatar. - Display-name helper explaining uniqueness within the parent's learner list. - Accessible DOB entry. - Approved-avatar picker with Remove avatar option. - Save changes primary action and Cancel secondary action. - Disable Save until a visible field differs from the loaded values. - Show inline duplicate-name, date and avatar errors. - On version conflict, explain that the profile changed elsewhere, reload current values and require review before resubmission. - Do not show owner, subscription, progress, mastery, status, pause, archive, hide or delete controls. - Preserve safe form inputs after retryable errors. - Responsive at 320px and keyboard accessible. | W10: GET /v1/learners/{learnerId} Return the full parent-authorized editable learner read model: id, displayName, dateOfBirth, ageYears, ageMonths, ageAsOfDate, avatarId, version, createdAt, updatedAt. PATCH /v1/learners/{learnerId} Strict request: {displayName?, dateOfBirth?, avatarId?, expectedVersion, idempotencyKey}. avatarId:null removes avatar. Require at least one editable field. Reject learnerId, ownerParentId, householdId, status, subscription, entitlement, progress, mastery and all unknown fields. Response: {learner:{id,displayName,dateOfBirth,ageYears,ageMonths,ageAsOfDate,avatarId,version,updatedAt}, changedFields, noOp}. All endpoints check parent account status and ownership before returning learner data. | X10: Alter learners: - version integer not null default 1 if not already present. - updated_at timestamptz not null default now(). Create learner_profile_update_requests: - parent_user_id uuid not null - learner_id uuid not null references learners(id) - idempotency_key uuid not null - request_hash text not null - expected_version integer not null - result_version integer null - status text not null check in ('processing','completed','failed') - response_json jsonb null containing only the safe API result - created_at timestamptz not null - completed_at timestamptz null - primary key(parent_user_id, learner_id, idempotency_key) Use existing append-only audit/outbox infrastructure for learner_profile_changed. Store changed field names and versions, not raw before/after DOB or display-name values. No learner status, paused_at, archived_at, deleted_at or lifecycle-history table. | Y10: Authenticate and verify the active parent before learner lookup. Authorize direct owner_parent_id equality for Version 1. Return LEARNER_NOT_FOUND for unauthorized learner IDs. Strictly reject protected/unknown fields to prevent mass assignment. Do not log display name or raw DOB in infrastructure logs. Do not include raw field values in routine analytics or audit events. Rate-limit update attempts. Use database uniqueness to protect concurrent name corrections. Soft-deleted/suspended parent status is checked before read and write. Self-learner profiles use the same rules and receive no parent-account privilege inside learning apps. | Z10: GET/PATCH p95 under 1.5 seconds excluding transient infrastructure latency. Correction transaction is atomic. Optimistic concurrency prevents lost updates. Idempotent replay is deterministic. Unicode and international names remain supported. Age calculation is deterministic for explicit as-of date and parent timezone. UI meets WCAG keyboard, labels, focus and error requirements. No correction changes subscriptions, entitlements, progress, mastery or session counters. | AA10: AC1 Owning active parent can correct display name, DOB and avatar. AC2 Learner UUID and owner_parent_id never change. AC3 Name correction follows LP-001 normalization and uniqueness. AC4 Capitalization-only correction for the same learner succeeds. AC5 Another owned learner's normalized name is rejected. AC6 Invalid or future DOB is rejected; adult DOB is accepted. AC7 DOB correction updates derived age context for future sessions. AC8 DOB correction does not reset placement, mastery, progress, completed work or weekly usage. AC9 Existing active app session keeps its original context snapshot. AC10 Avatar can be changed or removed; unapproved avatar is rejected. AC11 Protected and unknown fields are rejected. AC12 A material correction increments version exactly once. AC13 Exact no-op returns success without version increment or change event. AC14 Stale expectedVersion is rejected without overwriting data. AC15 Same idempotency key/payload returns the original result. AC16 Conflicting idempotency-key reuse is rejected. AC17 Concurrent duplicate-name corrections produce one success and one conflict. AC18 One change event records field names and version transition without raw DOB/name values. AC19 Unrelated parent cannot discover or update the learner. AC20 Suspended or soft-deleted parent cannot read or correct learners. AC21 Correction does not alter subscriptions or entitlements. AC22 Correction does not alter progress, mastery, sessions or weekly usage. AC23 No pause, archive, restore, hide, merge, transfer or delete UI/API exists. AC24 Self-learner profiles follow the same correction and security rules. AC25 Transaction failure leaves profile, version, idempotency and audit state unchanged. | AB10: LP-001; parent account-status middleware; approved-avatar registry; learner name-normalization and age utilities; audit/outbox infrastructure. | AC10: Simple correction avoids overlapping lifecycle states; commercial access remains entirely controlled by subscription and entitlement validity. | AE10: Implement permanent learner-profile correction only. Create the edit route, strict GET/PATCH APIs, optimistic versioning, parent+learner-scoped idempotency and change-event audit. Editable fields are displayName, dateOfBirth and avatarId only. Do not implement learner pause, archive, restore, hide, merge, ownership transfer, reset or deletion. Do not modify subscriptions, entitlements, progress, mastery, active sessions or weekly usage. An exact no-op must not increment version or write an event. DOB correction affects derived context only from the next session. Check parent account_status and direct ownership before returning data. Exact build packet: CBS-LP-002 | AF10: AT-LP-002-01 through AT-LP-002-25 | AG10: 1.0 | AH10: Product Owner | AI10: 2026-07-30
A11: LP-003 | B11: EP-LEARNER-01 | C11: Deferred Learner Access | D11: Additional Guardian Access | E11: Additional guardian access at learner level | F11: Should Have | G11: Deferred | H11: No | I11: Deferred | J11: Functional | K11: Babysteps Platform | L11: Parent | M11: As a learner-owning parent, I may later want to grant another trusted adult access to one specific learner without sharing my password or creating a household. | N11: Deferred outside the Version 1 baseline. Version 1 supports exactly one owning parent for each learner and does not implement invitations, additional guardian accounts, shared learner management or guardian continuity. | O11: 1. Do not implement learner guardian invitations in Version 1. 2. Do not create learner_guardian_access, guardian invitation or learner-sharing tables. 3. Do not add guardian permission roles or guardian authorization branches to learner APIs. 4. Only learners.owner_parent_id authorizes parent management in Version 1. 5. Do not grant access based on shared email domain, phone, device or relationship claims. 6. Do not allow another adult to view, correct, launch or manage an owned learner. 7. Do not create household-wide access as a substitute. 8. When the owning parent is suspended or soft deleted, no other adult receives continuity access. 9. The requirement remains visible for future reconsideration because secure invitation, consent, revocation and dispute-handling rules would be required before activation. | P11: No implementation prerequisite because the requirement is deferred. | Q11: Future reconsideration only after evidence that multiple-adult learner management is required. | R11: No Version 1 flow. Do not display Add guardian, Share learner, Invite parent or equivalent controls. | S11: If an unimplemented guardian route or field is requested, return a normal unsupported/not-found response without exposing learner data. | T11: None in Version 1. | U11: None in Version 1. | V11: No guardian invitation, sharing, permission or learner-continuity UI. | W11: No guardian invitation, acceptance, revocation or shared-learner APIs. | X11: Do not create guardian-access or invitation tables, columns, tokens or permission records. | Y11: Version 1 authorization remains direct owner_parent_id equality only. No guardian authorization fallback exists. Do not share learner personal data with another adult or issue invitation tokens. | Z11: No additional guardian-path latency, availability or compatibility requirements exist in Version 1. Architecture scans must confirm that the deferred surface is absent. | AA11: AC1 No guardian invitation UI exists. AC2 No learner-sharing API exists. AC3 No guardian-access table exists. AC4 Learner management requires owner_parent_id. AC5 A second adult cannot access the learner. AC6 Owner soft deletion locks the learner for everyone. AC7 Deferred scope is excluded from Version 1 counts. | AB11: Future privacy/consent, invitation security, dispute resolution, session revocation and support-policy decisions. | AC11: Deferred to keep Version 1 authorization simple and avoid substantial invitation, consent, revocation and family-dispute complexity. | AE11: Do not implement LP-003 in Version 1. Do not create guardian invitations, guardian-access records, shared learner authorization or household substitutes. Retain direct owner_parent_id authorization only. | AF11: No Version 1 acceptance-test suite; deferred-scope architecture scans may verify absence. | AG11: 0.1-deferred | AH11: Product Owner | AI11: 2026-07-30
A12: LP-004 | B12: EP-LEARNER-01 | C12: Learner Profiles | D12: Learner Selection & Session Safety | E12: Active learner selection, scheduled app launch and interruption-safe sessions | F12: Must Have | G12: Approved | H12: Yes | I12: In Development | J12: Functional | K12: Babysteps Platform | L12: Parent and Learner | M12: As a parent and learner, we want to select the correct learner, open only that learner's scheduled subscribed app, prevent simultaneous use of one learner profile, and safely resume an accidentally interrupted 45-minute session without consuming another weekly session. | N12: Babysteps shall establish an explicit, server-authorized learner context before app launch. A parent with more than one learner must select a learner; a parent with exactly one learner may have that learner selected automatically. The learner home shall show only the selected learner's entitled apps and enable session start only for the app currently authorized by the central schedule. Each learner may have at most one active or resumable learning session across all apps and devices. No user override of an ongoing session is permitted. A session interrupted by accidental browser closure, crash or connectivity loss may resume as the same session on the original device/browser within a 15-minute cumulative recovery allowance. Each learner receives two normal 45-minute sessions per week per entitled app; sessions are consumed at start, and any additional replacement session requires an audited administrator credit based on session logs. | O12: 1. A parent owning more than one learner must explicitly select a learner before entering learner home or seeing launchable apps. 2. A parent owning exactly one learner may be auto-selected after authentication. Zero learners routes to learner creation. 3. Learner selection is stored only for the current authenticated parent session and is cleared on logout, session expiry or account change. A multi-learner account must select again after a new login. 4. The selected learner must be carried by immutable learner UUID through learner home, schedule authorization, app launch, learning-session token, heartbeats and progress writes. Display name or browser state is never authoritative. 5. Learner home returns only the selected learner's entitlements, weekly usage and schedule state. Other learners' commercial or progress data is never mixed into the response. 6. Entitled apps may be displayed for orientation, but Start is enabled only for an app carrying a current server-issued schedule authorization. LP-004 consumes the schedule decision and does not calculate pedagogy or scheduling order. 7. Every learning-session start revalidates active parent account, direct learner ownership, selected learner context, entitlement, schedule authorization, weekly capacity and concurrent-session state. 8. Each learner may have at most one learning session in starting, active or disconnected/resumable state across all apps and devices. 9. Consequently, a parent owning N learner profiles can have at most N simultaneous reserved learning sessions, with no more than one belonging to each learner. Parent dashboard/authentication sessions do not count. 10. Different learners owned by the same parent may learn simultaneously on different devices when each independently passes entitlement, scheduling and weekly-capacity checks. 11. If the same learner is selected on another device while a session is active or resumable, display a session-in-progress popup and reject a new start. Do not offer takeover, override or End other session. 12. Starting a different app for the same learner is also blocked while any learning session for that learner is active or resumable. 13. A normal qualifying session start atomically consumes the next of two weekly slots for the learner_id + app_id + week_key. Retries with the same idempotency key return the same session and never consume twice. 14. Weekly capacity is two normal sessions per learner per app. A bundle retains a separate two-session allowance for each included app. 15. The week key is calculated server-side using the learner's stored timezone and ISO week beginning Monday 00:00. It is persisted at session start and is never client supplied. A timezone change may take effect only at the next week boundary. 16. A learning session provides at most 2,700 seconds of connected session time. Disconnected recovery time does not count toward the 45-minute session clock. 17. The app sends an authenticated heartbeat every 30 seconds. The server records last_heartbeat_at, connected_elapsed_seconds and verified_active_seconds; each heartbeat may add no more than the elapsed server interval and never trusts a client-total counter. 18. On an authenticated close/pagehide beacon, crash, connection loss or missed heartbeat, the session becomes disconnected/resumable. The server uses the close beacon when received; otherwise it derives disconnection from the last confirmed heartbeat. 19. The same session may resume only on the original device/browser using its valid device binding and resume credential. 20. The first interruption allows resume until disconnected_at + 15 minutes. Across repeated interruptions, cumulative disconnected time may not exceed 900 seconds; the effective deadline is limited by the remaining cumulative allowance. 21. Resume preserves session_id, learner_id, app_id, week_key and weekly slot number. It does not create a session row, consume a weekly slot or change the scheduled app. 22. During the recovery window, the learner session remains reserved and blocks every new start for that learner on every device. 23. If resume does not occur before the deadline, a server sweeper or the next session operation finalizes the session as interrupted, releases the learner lock and rejects future resume attempts. 24. Session states are starting, active, disconnected, completed, interrupted, expired and revoked_by_admin. There is no superseded or user-overridden state. 25. A session is conclusively considered used when verified_active_seconds is at least 1,350 seconds, which is 50% of 45 minutes. It is ineligible for a replacement credit. 26. A session below 1,350 verified active seconds remains consumed by default and is never restored automatically. The parent may contact support, and an administrator may grant one audited replacement credit only after reviewing platform logs and confirming a credible technical interruption. 27. A replacement credit is tied to one original session, learner and app; one original session may produce at most one credit. The credit does not alter or delete the original session. 28. A valid unused replacement credit authorizes one additional session for the same learner and app without increasing the two normal slots. It still requires valid entitlement, schedule authorization and no concurrent learner session. 29. Admin credit creation and evidence workflow are implemented in the Administration building block. LP-004 defines and consumes the replacement-credit contract. 30. Closing voluntarily, switching devices, attempting a concurrent start or remaining idle does not automatically qualify for a replacement credit. 31. When a parent account is suspended or soft deleted, selection and learner-home access are denied and all learning-session tokens stop working according to IA-003. 32. Progress writes require the active session token and exact learner/app binding. Completed, interrupted, expired, revoked or foreign tokens are rejected. 33. App session and progress ownership never changes when the parent switches the launcher to another learner. 34. There is no API, UI or hidden parameter that lets a parent or learner override an ongoing session. | P12: LP-001 and LP-002 are implemented. Parent authentication/account-status checks, app registry, schedule authorization, entitlements, progress adapter, platform session store, audit/outbox and administrative replacement-credit service contracts are available or stubbed behind stable interfaces. | Q12: Parent signs in, opens the learner launcher, selects a learner when required, or a learner opens Child access through a valid restricted authentication session. | R12: Selection and launch: 1. Server loads learners owned by the active parent. 2. Zero learners routes to Add learner; one learner is auto-selected; more than one displays learner cards and requires explicit selection. 3. Server stores selected_learner_id against the current parent authentication session. 4. Learner home loads only that learner's entitlement summaries, schedule decision, weekly usage and any active/resumable session state. 5. If an existing session is reserved, show the conflict/recovery popup and disable new starts. 6. Otherwise enable Start only on the server-authorized scheduled app. 7. Start request revalidates all gates, locks learner/session and weekly-usage rows, allocates normal slot 1 or 2 or consumes a valid replacement credit, creates the session and returns a learner/app-bound launch token. Normal session: 8. App opens with the signed launch/session token and sends 30-second heartbeats. 9. Server accumulates connected and verified-active time and accepts learner/app-bound progress writes. 10. At 2,700 connected seconds or app completion, finalize completed and release the learner lock. Interruption and resume: 11. Close beacon or heartbeat loss moves the session to disconnected and establishes the remaining recovery deadline. 12. Reopening on the original device/browser presents the resume credential. 13. Server revalidates session/device/account and cumulative recovery allowance, returns the same session, and continues the remaining connected time. 14. No resume before deadline finalizes interrupted and releases the lock. 15. Another device always receives a no-override conflict popup while the lock remains reserved. | S12: Multiple learners but none selected: LEARNER_SELECTION_REQUIRED. Selected learner not owned: LEARNER_NOT_FOUND and clear selection. Parent soft deleted/suspended: ACCOUNT_DELETED or ACCOUNT_SUSPENDED before learner data. No entitlement: APP_ENTITLEMENT_REQUIRED. No current schedule authorization: APP_SESSION_NOT_SCHEDULED. Two normal slots consumed and no valid replacement credit: WEEKLY_SESSION_LIMIT_REACHED. Active/disconnected session for learner: LEARNER_SESSION_ALREADY_IN_PROGRESS with safe conflict metadata; never offer override. Original device within recovery window: resume same session. Different device/browser resume attempt: SESSION_RESUME_DEVICE_MISMATCH. Recovery deadline passed: SESSION_RESUME_WINDOW_EXPIRED. Cumulative 900-second allowance exhausted: SESSION_RESUME_LIMIT_REACHED. Invalid/revoked/ended token: SESSION_NOT_ACTIVE. Duplicate start same idempotency key/payload: return original session. Same key with different payload: IDEMPOTENCY_KEY_REUSED. Concurrent starts: one transaction succeeds; others return conflict/weekly-limit without duplicate slot. Heartbeat replay/out-of-order: ignore safely using sequence/version. App progress write with wrong learner/app/session: deny and audit. Below-50% interruption: remains consumed; show Contact support, not automatic restoration. Above/equal-50% interruption: used and replacement-ineligible. Replacement credit invalid, expired, consumed or for another learner/app: do not authorize extra start. Sweeper failure: lazy finalization on next start/resume/current-session operation preserves the same outcome. | T12: Parent authentication session; learnerId selection; appId; signed schedule authorization; entitlement; server-derived weekKey; start idempotencyKey; secure deviceSessionId cookie; session/resume token; heartbeat sequence and app activity state; progress version; optional valid replacementCreditId selected server-side. | U12: Session-scoped selected learner; learner-home model; session conflict state; launch/session token; learner session record; weekly usage row; connected/verified-active timing; resumable deadline; finalized state; audit/outbox events; replacement-credit consumption when applicable. | V12: Routes/screens: - /learners/select for multi-learner selection. - /learners/{learnerId}/home for selected learner home. - App launch transition screen. - Session-in-progress popup. - Interrupted-session resume prompt on original device. Selection UI: - One card per learner with display name and avatar. - No learner is preselected when more than one exists after a new login. - Current authenticated-session selection may persist until logout/expiry. - A clear Switch learner action from learner home. Learner home: - Prominently show selected learner name/avatar. - Show only selected learner's subscribed/entitled apps. - Highlight the scheduled app; only it has an enabled Start session action. - Show weekly usage such as Session 1 of 2, Session 2 of 2, or replacement available. - Non-scheduled entitled apps may show next-status information but no Start action. Conflict popup: Heading: A learning session is already in progress. Body: Continue on the original device. A second session cannot be started until the current session ends or its recovery window expires. Actions: Go back; Contact support. Never show Override, Take over, End other session or Continue here. Do not expose device identifiers or sensitive activity. Resume UI: - Original device may show Resume session and remaining connected time. - Explain that resuming continues the same weekly session. - After expiry show Session can no longer be resumed and Contact support. - Fully keyboard accessible, responsive at 320px and safe for child use. | W12: GET /v1/learner-selection Return owned learner summaries, selectedLearnerId for current parent session and requiresSelection. PUT /v1/learner-selection Strict request {learnerId}; set current-session selection after active-owner authorization. Idempotent. GET /v1/learner-home Require selected learner; return selected learner summary, entitled app summaries, authoritative scheduledApp, weekly usage and currentSessionConflict. Never return other learners' data. GET /v1/learner-sessions/current?learnerId= Return safe active/disconnected state for owner/learner authentication context. POST /v1/learner-sessions/start Strict request {learnerId,appId,scheduleAuthorization,idempotencyKey}. Device binding comes from secure server-issued cookie. Atomically validate and start normal slot or valid server-selected replacement credit. Return sessionId, launchToken, weeklySlotNumber or replacement indicator, connectedSecondsRemaining and heartbeatIntervalSeconds=30. POST /v1/learner-sessions/{sessionId}/heartbeat Strict request {sequence,activityState,progressVersion?}. Authenticate session token/device binding. Update server timing and return status/remaining time. POST /v1/learner-sessions/{sessionId}/disconnect Best-effort authenticated sendBeacon endpoint. Marks disconnected; heartbeat fallback remains authoritative when beacon is absent. POST /v1/learner-sessions/{sessionId}/resume No new session or weekly slot. Requires original device binding and resume credential; returns refreshed session token for same session. POST /v1/learner-sessions/{sessionId}/complete Idempotently finalize completed, persist final progress checkpoint and release lock. No override, takeover or user-forced termination endpoint exists. | X12: learner_selection_contexts: - parent_session_id uuid primary key references platform_sessions(id) - parent_user_id uuid not null - selected_learner_id uuid not null references learners(id) - selected_at timestamptz not null - expires_at timestamptz not null learner_app_week_usage: - learner_id uuid not null - app_id text not null - week_key text not null - week_timezone text not null - normal_sessions_started smallint not null default 0 check between 0 and 2 - version integer not null default 1 - updated_at timestamptz not null - primary key(learner_id,app_id,week_key) learner_sessions: - id uuid primary key - learner_id uuid not null references learners(id) - app_id text not null - parent_user_id uuid not null - parent_session_id uuid null - device_session_id uuid not null - week_key text not null - week_timezone text not null - weekly_slot_number smallint null check in (1,2) - replacement_credit_id uuid null - source text not null check in ('normal','replacement') - status text not null check in ('starting','active','disconnected','completed','interrupted','expired','revoked_by_admin') - schedule_authorization_id text not null - started_at timestamptz not null - last_heartbeat_at timestamptz not null - disconnected_at timestamptz null - resume_deadline timestamptz null - cumulative_disconnected_seconds integer not null default 0 check between 0 and 900 - connected_elapsed_seconds integer not null default 0 check between 0 and 2700 - verified_active_seconds integer not null default 0 check >=0 - heartbeat_sequence bigint not null default 0 - resume_token_hash text not null - ended_at timestamptz null - end_reason text null - version integer not null default 1 - created_at / updated_at timestamptz not null Retention: learner_sessions is operational current/resumable state. After finalization and successful propagation to compact progress, lesson completion, daily analytics buffer and any explicitly opened support case, delete or purge finalized session detail according to FC-DATA-001. Do not retain permanent completed-session history. Indexes/constraints: - unique partial index on learner_id where status in ('starting','active','disconnected'). - unique(learner_id,app_id,week_key,weekly_slot_number) where source='normal'. - unique replacement_credit_id where non-null. - source='normal' requires weekly_slot_number and null replacement credit; source='replacement' requires null normal slot and a replacement credit. session_start_requests: - actor_session_id uuid, learner_id uuid, idempotency_key uuid composite primary key - request_hash, session_id, status, timestamps and safe response. session_replacement_credits contract: - id uuid primary key - original_session_id uuid not null unique - learner_id uuid not null - app_id text not null - granted_by_admin_id uuid not null - reason_code text not null - evidence_summary text not null - granted_at timestamptz not null - valid_from timestamptz not null - expires_at timestamptz not null - status text available|consumed|expired|revoked - consumed_session_id uuid null unique - consumed_at timestamptz null Grant endpoint is owned by Administration; LP-004 consumes only available, unexpired, matching credits. | Y12: All selection, home and session operations are server-authoritative. Direct owner_parent_id authorization applies for parent flows; restricted learner authentication sessions are bound to one learner. Selected learner IDs from clients are reauthorized and never trusted as ownership proof. Learning-session and resume tokens are signed, short-lived, scoped to session/learner/app/device and stored in secure HttpOnly SameSite cookies where applicable. Use random device_session_id, not browser fingerprinting. No cross-device resume and no ongoing-session override. No device name, IP or detailed activity is shown in the conflict popup. Parent account status is checked on start/resume/heartbeat/progress writes. Raw heartbeat/activity data has restricted retention and is not used for advertising. Replacement credits are admin-only, append-only audited and cannot be granted automatically. Progress writes require current active session and exact learner/app binding. Rate-limit selection, start, resume and heartbeat abuse; heartbeats use sequence/version replay protection. Never trust client totals for elapsed or active seconds. | Z12: Selection/home/start p95 under 1.5 seconds excluding app redirect. Heartbeat p95 under 750 ms and safe under duplicate/out-of-order delivery. Session-start transaction must be serializable for one learner and learner-app-week usage. No more than one reserved session per learner under concurrency races. Weekly normal slot count never exceeds two. Resume decision is deterministic from server time, device binding and cumulative allowance. A background sweeper finalizes stale sessions, with lazy finalization as a correctness fallback. Session/progress state remains recoverable after browser closure and platform restart. UI is WCAG keyboard accessible and usable at 320px. Operational logs support administrator review without exposing unnecessary learner content. Finalized session detail must not become permanent history; current/resumable state is retained only until required propagation and support handling complete. | AA12: AC1 Multi-learner parent must explicitly select before learner home. AC2 Single-learner parent is auto-selected; zero learners routes to creation. AC3 Selection clears on logout/expiry and multi-learner account selects again next login. AC4 Learner home contains only selected learner data and entitled apps. AC5 Only server-authorized scheduled app can start. AC6 Launch/progress use immutable learner UUID, not name or cached UI state. AC7 One learner has at most one starting/active/disconnected session across apps/devices. AC8 Parent with N learners can have at most N reserved sessions and different learners may run concurrently. AC9 Same learner on another device receives conflict popup and no override action. AC10 Different-app start for same learner is blocked while session reserved. AC11 Normal start consumes one weekly slot exactly once. AC12 Each learner-app has two normal weekly slots; third normal start is rejected. AC13 Second normal session may start only after first is finalized and schedule allows. AC14 A second-session-in-progress blocks every further start; after completion the weekly limit still blocks. AC15 Heartbeats occur every 30 seconds and server owns elapsed counters. AC16 Accidental close creates disconnected/resumable state. AC17 Original device/browser resumes same session within remaining 15-minute cumulative allowance. AC18 Resume consumes no new weekly slot and preserves week/app/session identity. AC19 Different device cannot resume. AC20 Recovery time does not count toward 45 connected minutes. AC21 Cumulative disconnected time cannot exceed 900 seconds. AC22 Expired recovery finalizes interrupted and releases learner lock. AC23 Cross-week resume retains original week key and slot. AC24 At least 1,350 verified active seconds makes session used and replacement-ineligible. AC25 Below 1,350 remains consumed with no automatic restoration. AC26 Admin-reviewed valid replacement credit permits one additional same-learner/app session. AC27 One original session cannot receive or consume more than one replacement credit. AC28 Replacement session still requires entitlement, schedule and free learner concurrency. AC29 Voluntary exit/device switch/concurrent attempt does not automatically create credit. AC30 Duplicate start/reconnect/heartbeat requests do not double-consume or double-count. AC31 Concurrent start race yields one session only. AC32 Old/ended/foreign session tokens cannot write progress. AC33 Soft-deleted/suspended parent immediately loses selection, launch, resume and progress access. AC34 No override/takeover/end-other-session endpoint or UI exists. AC35 Session conflict and resume UI are accessible and disclose no device-sensitive details. | AB12: LP-001; LP-002; IA-003; IA-004 authentication-session distinction; app registry; app scheduling contract; billing/entitlements; progress persistence; platform sessions; audit/outbox; future admin replacement-credit grant workflow. | AC12: A visible learner path and scheduled primary action preserve motivation, while strict learner/session binding prevents progress corruption and enforces deliberate two-session weekly cadence. | AE12: Implement the multi-learner selector, session-scoped learner context, selected learner home, scheduled-app launch gate, one-reserved-session-per-learner enforcement, two normal weekly slots per learner/app, no-override conflict UI, 45-minute server-timed sessions, 30-second heartbeats, 15-minute cumulative same-device resume, interruption finalization and replacement-credit consumption contract. Do not calculate pedagogy/scheduling in this module; consume a signed schedule authorization. Do not revoke or replace an ongoing learning session from another device. A normal session slot is allocated exactly once at start. A resume reuses the same session and slot. At 1,350 verified active seconds or more, replacement is forbidden. Below that threshold there is no automatic restoration; only a valid admin credit may authorize one extra same-app session. Ensure every progress write is bound to active session + learner + app. Exact build packet: CBS-LP-004 | AF12: AT-LP-004-01 through AT-LP-004-35 | AG12: 1.0 | AH12: Product Owner | AI12: 2026-07-30
A13: AR-001 | B13: EP-APPREG-01 | C13: App Registry | D13: Admin App Registration | E13: Admin-managed canonical app registration and soft deletion | F13: Must Have | G13: Approved | H13: Yes | I13: Done | J13: Functional | K13: Babysteps Platform | L13: Platform Administrator | M13: As an authorized platform administrator, I want to register and manage Babysteps learning apps through a dedicated admin page so every platform relationship uses one permanent app identity and an app can be removed from operation without deleting its identity or historical references. | N13: Babysteps shall provide a Version 1 App Registry administration page and privileged APIs for creating, viewing and editing app registrations, activating draft apps, soft-deleting apps and restoring soft-deleted apps. Every app receives one permanent UUID and one globally unique immutable app_key. Soft deletion is the only deletion mechanism; no hard-delete operation exists. Soft deletion immediately blocks new operational activity while retaining the minimal app identity required to interpret existing references. | O13: 1. The dedicated admin route is /admin/apps with create, details, edit, activate, soft-delete and restore actions. 2. Only an authenticated administrator with the relevant app-registry permission may use registry mutation APIs. 3. Public users, parents, learners, browser apps and learning-app services cannot self-register or mutate app records. 4. Every app has an immutable UUID primary key and immutable globally unique app_key. 5. app_key is lowercase ASCII, hyphen separated, begins with a letter, contains only a-z, 0-9 and hyphen, and is 2–50 characters: ^[a-z][a-z0-9-]{1,49}$. 6. display_name is required, trimmed plain text, 1–80 visible characters and may be rebranded without changing app identity. 7. short_description is required before activation, plain text only and 1–240 characters. 8. icon_asset_key must reference an active approved platform asset before activation. Arbitrary remote icon URLs are prohibited. 9. category and owning_team are required before activation and are mutable descriptive metadata only. 10. Initial registry states are draft, active and soft_deleted. 11. A new app is created in draft. Draft apps cannot be mapped to commercial products, granted as entitlements, scheduled or launched. 12. Activation requires complete valid metadata and environment configuration readiness supplied by AR-002; activation is version checked and audited. 13. The initial Chess Master, Magical Math and Speed Reader apps shall be registered through the same admin-controlled service. A bootstrap script may call the service idempotently but must not bypass its validation or identity rules. 14. All subscriptions, product mappings, entitlements, schedules, sessions, progress and analytics aggregates reference app_registry.id through app_id. 15. app_key may be used in URLs/configuration, but database foreign keys and authorization use app_id. 16. Unknown app IDs and app keys fail closed. No entitlement, progress, analytics or launch request implicitly creates an app. 17. Mutable fields are display_name, short_description, icon_asset_key, category, owning_team and internal operational notes. 18. Immutable fields are id, app_key and created_at. Attempted mutation is rejected. 19. Every app row has version integer not null default 1; material mutations require expectedVersion and increment version exactly once. 20. Every mutation requires an administrator-scoped idempotency key. Same key and same payload returns the original result; different payload returns IDEMPOTENCY_KEY_REUSED. 21. Soft deletion is the only delete action. There is no hard-delete API, UI, SQL function or normal operational procedure. 22. Soft deletion requires recent administrator reauthentication, app_registry_soft_delete permission, a mandatory reason code, optional concise reason note and exact typed confirmation of the app_key. 23. Soft deletion atomically sets registry_status=soft_deleted, records soft_deleted_at, invalidates active launch/schedule authorizations and emits app_soft_deleted. 24. Soft deletion blocks new product mappings, subscriptions for that app, entitlements, schedules, launches, sessions, progress writes and app-originated analytics buffer updates. 25. Soft deletion removes the app from learner and parent launch surfaces but retains app_id, app_key and last display_name so historical references remain interpretable. 26. Soft deletion does not delete learner progress, completed lessons, financial records or already finalized anonymous analytics aggregates; each related table follows its own approved retention policy. 27. Soft deletion does not automatically refund, cancel or reassign subscriptions. Billing requirements own customer remediation. 28. Restore requires app_registry_restore permission, recent reauthentication, reason and expectedVersion. 29. Restore returns the app to draft, not active. Configuration and activation checks must pass again. 30. app_key remains permanently reserved through soft deletion and restoration. 31. App registry reads expose only safe metadata. Secrets, signing keys, environment credentials, private repository URLs and internal incident contacts are excluded. 32. Registry mutations write a minimal audit event with app ID/key, operation, administrator ID, reason code, version transition and timestamp. Do not store duplicate metadata snapshots indefinitely. 33. Routine list queries exclude soft-deleted apps unless includeSoftDeleted=true is requested by an authorized admin. 34. Learning services may read active safe metadata but have no write permission. 35. All changes are transactional and strict-schema validated; unknown and protected fields are rejected. | P13: Platform administrator authentication, authorization roles, approved asset registry, audit/outbox and AR-002 environment-readiness adapter exist or are available behind stable interfaces. | Q13: An authorized administrator opens /admin/apps and chooses Register app, Edit, Activate, Soft delete or Restore. | R13: Create: 1. Admin enters app_key and initial metadata. 2. Client validates visible fields and submits with idempotency key. 3. Server authorizes app_registry_create. 4. Server strictly validates key and metadata and checks global uniqueness. 5. Server creates a draft app with generated UUID and version 1. 6. Audit event is written atomically and the admin sees the app detail page. Activate: 7. Server locks the draft row, verifies expectedVersion, complete metadata and AR-002 readiness. 8. Status changes to active, version increments and app_activated is emitted. Edit: 9. Admin updates only mutable fields using expectedVersion and idempotency. 10. Exact no-op returns current row without version increment or event. Soft delete: 11. Admin opens impact summary, reauthenticates, selects reason and types app_key. 12. Server locks the app, verifies active/draft state, permission, confirmation and expectedVersion. 13. Status changes to soft_deleted; outstanding launch/schedule authorizations are invalidated and downstream blockers are emitted. 14. Learner/parent surfaces stop showing the app. 15. Historical references remain valid. Restore: 16. Admin reauthenticates and supplies reason. 17. Server changes soft_deleted to draft, increments version and requires later activation checks. | S13: Duplicate key: APP_KEY_ALREADY_EXISTS. Invalid key: APP_KEY_INVALID. Incomplete/invalid metadata: APP_METADATA_INVALID. Invalid/inactive icon: APP_ICON_NOT_AVAILABLE. Unknown app: APP_NOT_FOUND. Immutable field mutation: APP_IDENTITY_IMMUTABLE. Unknown/protected field: FORBIDDEN_FIELD. Stale expectedVersion: APP_VERSION_CONFLICT. Conflicting idempotency reuse: IDEMPOTENCY_KEY_REUSED. Insufficient permission: FORBIDDEN. Recent reauthentication missing: REAUTHENTICATION_REQUIRED. Activation prerequisites missing: APP_NOT_READY_FOR_ACTIVATION. Already active/draft/soft-deleted transition no-op: return current state when semantically idempotent. Soft-delete typed confirmation mismatch: CONFIRMATION_MISMATCH. Soft-deleted app operational request: APP_NOT_ACTIVE. Restore always returns draft; direct restore-to-active is rejected. Transaction/downstream invalidation failure: roll back status/version/idempotency/event state. No hard-delete route exists; requests return not found/unsupported without deleting data. | T13: Create: appKey, displayName, shortDescription?, iconAssetKey?, category?, owningTeam?, internalNotes?, idempotencyKey. Edit/activate/delete/restore: expectedVersion, idempotencyKey and operation-specific reason/confirmation. Client never supplies app UUID on create. | U13: Permanent app UUID and immutable key; safe registry read model; draft/active/soft-deleted state; incremented version; minimal audit/outbox events; downstream invalidation event on soft delete. No physical deletion. | V13: Routes: - /admin/apps - /admin/apps/new - /admin/apps/{appId} - /admin/apps/{appId}/edit List: - Search by key/display name. - Filters for draft, active and soft deleted. - Soft-deleted records hidden by default with an explicit privileged filter. Create/edit: - Clearly mark app_key as permanent. - Plain-text metadata fields and approved icon picker. - Save as draft; activation is a separate explicit action. - Version-conflict reload and review. Soft delete: - Impact summary with safe counts of active products, entitlements and outstanding authorizations. - Mandatory reason code, optional note and exact app_key confirmation. - Warning that the app stops immediately but historical identity remains. - Only Soft delete; never display Hard delete. Restore: - Explain restoration returns to draft and requires reactivation. - Keyboard accessible, responsive at 320px, auditable confirmations and safe error recovery. | W13: GET /v1/admin/apps?status=&includeSoftDeleted= GET /v1/admin/apps/{appId} POST /v1/admin/apps PATCH /v1/admin/apps/{appId} POST /v1/admin/apps/{appId}/activate POST /v1/admin/apps/{appId}/soft-delete POST /v1/admin/apps/{appId}/restore Public/trusted read: GET /v1/apps GET /v1/apps/{appKey} Return only safe active app metadata unless trusted internal callers explicitly request draft/deleted records. Create strict payload excludes id/status/version/timestamps. Patch allows mutable metadata only. Activate requires expectedVersion and idempotencyKey. Soft-delete requires expectedVersion, idempotencyKey, reasonCode, optional reasonNote and confirmationAppKey. Restore requires expectedVersion, idempotencyKey and reasonCode. No DELETE method and no hard-delete endpoint/function exist. | X13: app_registry: - id uuid primary key default gen_random_uuid() - app_key text not null unique immutable - display_name text not null - short_description text null until activation - icon_asset_key text null until activation - category text null until activation - owning_team text null until activation - internal_notes text null - registry_status text not null check in ('draft','active','soft_deleted') default 'draft' - version integer not null default 1 - created_at timestamptz not null - updated_at timestamptz not null - activated_at timestamptz null - soft_deleted_at timestamptz null - soft_delete_reason_code text null - constraints for key/name/description lengths and state-field consistency app_registry_mutation_requests: - admin_user_id uuid not null - app_id uuid null for create - idempotency_key uuid not null - operation text not null - request_hash text not null - result_app_id uuid null - result_version integer null - status processing|completed|failed - safe_response_json jsonb null - created_at/completed_at - unique(admin_user_id,idempotency_key) Use existing audit/outbox. No app deletion tombstone, deleted_at field, hard-delete procedure or cascade delete path. | Y13: Admin APIs require verified active platform-admin authentication, recent reauthentication for activate/delete/restore and explicit least-privilege permissions. Browser and learning-app credentials are read-only and cannot access internal notes. Use server-side service credentials only. RLS/server repositories deny non-admin registry mutations. Strict field schemas prevent mass assignment. No secrets, signing keys or credentials in app_registry or safe responses. Soft-delete invalidation is transactional/outbox-driven and fails closed. Audit administrator ID and reason code without duplicating full metadata snapshots. Rate-limit mutations and confirmation failures. Foreign keys use RESTRICT for app identity relationships; no ON DELETE CASCADE from app_registry. Soft-deleted app keys remain reserved permanently. | Z13: Admin list/read p95 under 1.5 seconds; create/edit/transition p95 under 2 seconds excluding downstream propagation. App identity uniqueness is strongly consistent. Mutation transaction and outbox are atomic. Soft-delete becomes effective for new launch/session authorization immediately after commit. Read APIs are cacheable by version/status but must invalidate on mutation. UI is WCAG keyboard accessible and usable at 320px. Migrations are reversible without permitting physical deletion. The retained registry footprint is one compact row per app plus minimal mutation/audit records under their retention policies. | AA13: AC1 Dedicated /admin/apps page exists from Version 1. AC2 Authorized admin creates a draft app with generated UUID. AC3 app_key validation and global uniqueness are enforced. AC4 UUID and app_key are immutable. AC5 Display name and approved mutable metadata can be edited. AC6 Exact no-op does not increment version. AC7 Stale updates are rejected. AC8 Chess Master, Magical Math and Speed Reader use the same registration service. AC9 Draft app cannot be sold, entitled, scheduled or launched. AC10 Activation requires complete metadata and AR-002 readiness. AC11 Active app appears in safe registry reads. AC12 Browser/learning app cannot mutate registry. AC13 All platform relationships use app_id foreign keys. AC14 Unknown app keys/IDs fail closed and never auto-create. AC15 Admin can soft-delete draft or active app with reauth, permission, reason and exact key confirmation. AC16 Soft delete blocks all new operational use and removes learner/parent launch visibility. AC17 Soft delete invalidates outstanding launch/schedule authorization. AC18 Soft delete preserves permanent app identity and existing references. AC19 Soft delete does not delete progress, lessons, billing or finalized analytics aggregates. AC20 Soft delete does not automatically refund/cancel/reassign subscriptions. AC21 Admin can restore soft-deleted app to draft only. AC22 Restored app retains UUID/key and must reactivate separately. AC23 app_key remains reserved after soft deletion. AC24 Safe reads exclude secrets/internal notes. AC25 Minimal audit/outbox event records each mutation. AC26 Idempotent replay returns original result; key conflict is rejected. AC27 Concurrent same-key creation yields one app only. AC28 Transaction failure produces no partial state. AC29 Routine admin list hides deleted apps unless privileged filter is used. AC30 No hard-delete UI, API, SQL routine or cascade path exists. | AB13: Platform admin identity/RBAC; approved asset registry; AR-002 environment configuration; AR-003 availability controls; app launch; billing/products; entitlements; schedule; progress; analytics; audit/outbox. | AC13: A central app identity enables one learner launcher and consistent cross-app progress without allowing learning applications to become trust authorities. | AE13: Implement AR-001 exactly. Build the Version 1 /admin/apps registry UI and privileged APIs. Create immutable UUID/app_key identities, draft/active/soft_deleted states, optimistic versioning and admin-scoped idempotency. Soft delete is the only deletion mechanism. Do not implement hard delete, DELETE endpoints, deletion tombstones or ON DELETE CASCADE. Soft deletion must block new product, entitlement, schedule, launch, session, progress and analytics-buffer activity while preserving the minimal app identity and all referenced records under their own retention rules. Restore returns to draft. All platform foreign keys use app_id; unknown keys fail closed. Register Chess Master, Magical Math and Speed Reader through the same validated service/bootstrap path. Exact build packet: CBS-AR-001 | AF13: AT-AR-001-01 through AT-AR-001-30 | AG13: 1.0 | AH13: Product Owner | AI13: 2026-07-30
A14: AN-001 | B14: EP-OBSERVE-01 | C14: Analytics & Observability | D14: Daily Analytics Aggregation | E14: Minimal-data daily analytics aggregation | F14: Must Have | G14: Approved | H14: Yes | I14: Done | J14: Functional | K14: Babysteps Platform | L14: Platform Scheduler and Administrator | M14: As a platform owner, I want one daily aggregation run that answers usage, level-time and age-band questions without retaining permanent learner event histories. | N14: Babysteps shall collect only compact current operational state and one temporary daily analytics buffer row per learner pseudonym, app, level and activity date. At 00:15 Asia/Kolkata, one scheduled job processes the complete previous local calendar day, writes anonymous app-level and level-level aggregates using exact replacement, verifies totals, finalizes the date and deletes all temporary learner-level analytics rows. Permanent analytics tables shall contain no learner UUID, parent UUID, learner name, exact age or date of birth. | O14: 1. Standard analytics uses Asia/Kolkata calendar days in Version 1. 2. The daily job runs at 00:15 Asia/Kolkata and receives the explicit previous activity_date; it never infers its target only from server current date. 3. During learning, no raw analytics event, clickstream, page-view, navigation, keystroke, mouse movement, session replay or per-heartbeat row is inserted. 4. Heartbeats update the current learner session row in place. Server-confirmed intervals update one analytics_daily_buffer row in place. 5. Temporary buffer grain is activity_date + learner_daily_key + app_id + level_key. 6. learner_daily_key is HMAC-SHA256 using a dedicated analytics secret over learner_id and activity_date. It changes daily and is deleted with the buffer. 7. The analytics database never receives learner UUID, parent UUID, display name, raw DOB or exact age. 8. Age is derived from restricted DOB for the activity_date and immediately converted to one approved band: under_6, 6_7, 8_9, 10_12, 13_15, 16_18, 19_29, 30_49, 50_plus. 9. Buffer counters are engaged_seconds, sessions_started, sessions_completed, sessions_interrupted and lessons_completed. 10. engaged_seconds is calculated from server-confirmed active intervals and never from a client-submitted total. 11. Each source operation uses a deterministic contribution key or monotonic session checkpoint so retries do not double count. 12. sessions_started belongs to the date of the authoritative server start. 13. sessions_completed and sessions_interrupted belong to the date of finalization. 14. lesson completion belongs to the date the server accepts the idempotent completion. 15. For a session crossing midnight, connected/engaged seconds before midnight update the first date and seconds after midnight update the next date; the learning session and weekly slot remain unchanged. 16. The scheduled run obtains a single-date advisory/distributed lock. 17. The job creates or locks analytics_daily_runs for the target date and refuses concurrent processing. 18. The job reads all buffer rows for the date and calculates level aggregates grouped by date, app_id, level_key and age_band. 19. The job separately calculates app aggregates grouped by date, app_id and age_band directly from buffer rows so an active learner spanning multiple levels is counted once at app grain. 20. Aggregate writes use exact replacement/upsert values, never blind increments. 21. A rerun before deletion or an authorized repair run produces identical aggregate rows for identical buffer contents. 22. Before deletion, the job verifies source and aggregate totals for engaged seconds, sessions started, completed, interrupted and lessons completed. 23. Active learner counts are verified from distinct learner_daily_key at each aggregation grain and are not expected to sum across levels. 24. If any verification fails, aggregate transaction is rolled back or marked failed, the buffer remains intact and an administrator alert is emitted. 25. Only after aggregates are committed and the run is completed may buffer rows and daily pseudonymous keys be deleted. 26. analytics_daily_runs retains only date, state, source row count, source/aggregate control totals, timestamps and failure code; no learner information. 27. Permanent daily aggregates reference immutable app_id. Soft-deleted apps remain interpretable but generate no new buffer updates. 28. Permanent named learner history is limited to the compact learner_app_progress row and lesson_completions required for continuation and parent reporting. 29. learner_app_progress stores only current level/lesson, current unfinished engaged time, current app state, schema/version and updated_at; previous snapshots are not retained indefinitely. 30. lesson_completions stores one row per learner, app and lesson with level_key, completed_at, engaged_seconds and minimal result; no answer-by-answer or session history is required. 31. Standard administrator analytics is cohort based and provides no named-learner drill-down. 32. Anonymous aggregates may be retained for product trend analysis because they contain no learner identifier; retention review remains governed by privacy policy. 33. Current/resumable session data is retained only while operationally required. Finalized session detail is not kept as permanent analytics history. 34. Temporary support evidence required by LP-004 is not analytics data, must remain minimal and follows the explicit support-case retention policy; AN-001 must not duplicate it. 35. No analytics table or job may become the authoritative source for learner progress, weekly usage, entitlement or scheduling decisions. | P14: AR-001 permanent app identity; LP-001 restricted DOB/age derivation; LP-004 server-authoritative session timing; progress/lesson completion contracts; scheduler, secrets manager, audit/alerting and admin analytics read surface. | Q14: The platform scheduler invokes the daily aggregation job for the explicit previous Asia/Kolkata date. | R14: During day: 1. Current-session heartbeats update the current session row. 2. Server computes confirmed engaged-time delta and derives the learner's age band. 3. Service derives the date-specific HMAC learner_daily_key. 4. Buffer row is upserted by date/key/app/level using idempotent contribution tracking. 5. Session/lesson state transitions update the relevant counters exactly once. Daily run: 6. At 00:15 Asia/Kolkata, scheduler calls the job with previous activity_date. 7. Job acquires the date lock and creates/locks run row. 8. Job reads the frozen target-date buffer set. 9. It calculates level and app aggregates independently. 10. It writes exact aggregate values in a transaction. 11. It validates control totals and distinct counts. 12. On success, it marks completed and deletes target-date buffer rows. 13. On failure, it retains source rows, records failure and alerts admin. 14. Admin analytics reads only completed aggregate dates. | S14: Duplicate scheduler invocation: one run obtains lock; others return current run. Completed date invoked again after buffer deletion: return completed result without changing aggregates. Failed prior run: authorized retry reuses retained buffer and exact-replaces aggregates. Control-total mismatch: fail and retain buffer. Missing analytics secret: reject buffer write/job and alert; never fall back to plain learner ID. Unknown/inactive/soft-deleted app: reject new buffer contribution. Unknown level key: reject or route to explicit platform-defined unknown_level bucket only when contract allows; never silently drop time. Out-of-order heartbeat: monotonic checkpoint prevents negative/double delta. Session crosses midnight: split using server timestamps. Late network request after midnight: attribute by authoritative server interval/completion time, not client event timestamp. Lesson completion retry: unique completion/contribution key prevents duplicate count. Buffer deletion failure after completed aggregates: retry deletion safely; aggregates remain exact. Aggregate write failure: no deletion. Administrator queries a running/failed date: return status and only last completed aggregates. Small cohort privacy suppression, when later enabled, affects presentation and not source-control totals. | T14: Runtime inputs: current session ID, server timestamps, active-time delta, learner ID used only inside trusted service, app_id, level_key, activity date, derived age band, deterministic contribution ID, session/lesson transition. Job input: explicit activityDate. | U14: Temporary daily buffer; anonymous daily level/app aggregate rows; compact run status/control totals; current progress and lesson completions updated by their owning services. Successful run deletes temporary learner_daily_key rows. | V14: Administrator analytics route: - /admin/analytics - Date range, app, level and age-band filters. - Shows totals, averages and completion/interruption rates from completed daily aggregates. - Clearly labels incomplete/failed dates. - No learner search or named drill-down. - Soft-deleted app names remain resolvable through AR-001 identity. Operational run view: - /admin/analytics/runs - Date, running/completed/failed state, source row count, control totals and failure code. - Retry action requires analytics_run_retry permission. - Never displays learner daily keys or raw buffer rows in ordinary UI. Parent named reports are separate and use current progress plus lesson completions, not analytics aggregates. | W14: Internal contribution service: POST /v1/internal/analytics/daily-contribution Trusted platform service only; strict payload {activityDate, learnerId, appId, levelKey, ageBandDerivedServerSide, contributionId, deltas}. Prefer in-process service call/outbox over browser call. LearnerId is used transiently to derive daily key and is never persisted in analytics tables. Scheduled job: POST /v1/internal/analytics/daily-runs/{activityDate} Scheduler/service authentication; exact date; lock and idempotent run. Admin read: GET /v1/admin/analytics/daily?from=&to=&appId=&levelKey=&ageBand= GET /v1/admin/analytics/runs POST /v1/admin/analytics/runs/{activityDate}/retry No public/browser analytics-write endpoint and no raw-event ingestion endpoint. | X14: analytics_daily_buffer: - activity_date date not null - learner_daily_key bytea/text not null - app_id uuid not null references app_registry(id) on delete restrict - level_key text not null - age_band text not null check approved bands - engaged_seconds integer not null default 0 check >=0 - sessions_started/completed/interrupted integer not null default 0 check >=0 - lessons_completed integer not null default 0 check >=0 - last_contribution_checkpoint jsonb or version bigint not null - updated_at timestamptz not null - primary key(activity_date,learner_daily_key,app_id,level_key) analytics_contribution_receipts or compact checkpoint: - deterministic contribution_id unique - activity_date - expires with buffer after successful run Use the smallest mechanism compatible with exact-once deltas. analytics_daily_level: - activity_date, app_id, level_key, age_band composite primary key - active_learners - sessions_started/completed/interrupted - engaged_seconds - lessons_completed - generated_at, run_version analytics_daily_app: - activity_date, app_id, age_band composite primary key - same metrics - generated_at, run_version analytics_daily_runs: - activity_date primary key - status running|completed|failed - run_version - source_row_count - source and aggregate control totals - started_at/completed_at - failure_code - no learner identifiers learner_app_progress and lesson_completions remain outside analytics ownership and follow the compact fields in the requirement. | Y14: Analytics secret is separate from authentication/signing secrets and stored only in the secrets manager. Use HMAC, never an unhashed learner UUID or predictable hash. Daily keys change with activity_date and are deleted after aggregation. Analytics DB roles cannot read learner profiles/DOB. Age band derivation occurs in a trusted platform service; exact DOB is not logged. Internal contribution and job endpoints require service authentication and replay protection. Admin analytics requires least-privilege read; retry requires separate permission and reauthentication when appropriate. No raw buffer exposure in ordinary admin UI. No browser analytics ingestion. Rate-limit and authenticate internal calls; log request IDs without learner IDs/daily keys. Aggregate tables contain no direct or stable pseudonymous learner identifier. Soft-deleted apps reject new contributions. Privacy policy controls aggregate retention and small-cohort display rules. | Z14: Buffer updates p95 under 500 ms or asynchronously committed through reliable outbox without blocking learning UX. Daily run completes within 30 minutes for Version 1 load and is restart safe. One run per date executes at a time. Control totals must match before deletion. Successful run leaves zero target-date buffer rows. Repeated run is deterministic. No raw event-table growth. Aggregation supports at least date/app/level/age-band filters. Scheduler and job monitoring alert on missed, failed or overdue runs. All timestamps are UTC internally with explicit Asia/Kolkata date derivation. Migrations and cleanup jobs are testable and reversible without restoring purged pseudonymous rows. | AA14: AC1 No permanent raw analytics event or heartbeat table exists. AC2 Current session heartbeat updates rows in place. AC3 One temporary buffer row exists per date/daily-key/app/level. AC4 Daily key is HMAC-derived, changes daily and no learner UUID is stored. AC5 Exact DOB/age/name/parent ID are absent from analytics storage. AC6 Approved age band is derived for activity date. AC7 Engaged seconds use server-confirmed intervals. AC8 Contribution retries do not double count. AC9 Job runs at 00:15 Asia/Kolkata for explicit previous date. AC10 Concurrent invocation produces one active run. AC11 Level aggregates are correct by date/app/level/age band. AC12 App aggregates count one learner once per app/day/age band even across levels. AC13 Aggregate writes exact-replace rather than increment. AC14 Session crossing midnight splits engaged time correctly. AC15 Started/completed/interrupted/lesson counters use defined authoritative dates. AC16 Control totals match before deletion. AC17 Verification failure retains buffer and marks failed. AC18 Successful run deletes all target-date buffer rows and daily keys. AC19 Rerun/retry is deterministic. AC20 Run tracking contains no learner identifiers. AC21 Soft-deleted app receives no new contributions. AC22 Final aggregates reference permanent app_id. AC23 Admin analytics has no named learner drill-down. AC24 Current named learner report comes only from compact progress and lesson completions. AC25 One lesson completion row exists per learner/app/lesson and includes engaged seconds. AC26 Repeated progress snapshots are not retained indefinitely. AC27 No client-submitted active-time total is authoritative. AC28 Unknown/protected analytics fields are rejected. AC29 Missing secret fails closed without persisting identifiable fallback. AC30 Buffer deletion failure can retry without changing aggregate totals. AC31 Internal job/write endpoints are unavailable to browsers. AC32 Failed/running dates are labelled and excluded from complete reports. AC33 Analytics is not used as source of truth for progress/access/scheduling. AC34 Finalized session detail is not retained as permanent analytics history. AC35 Temporary support evidence is not copied into analytics. | AB14: AR-001; LP-001; LP-004; progress storage and lesson completion contracts; scheduler; secrets manager; admin RBAC; audit/alerting; privacy retention and future observability requirements. | AC14: Daily cohort aggregates preserve insight into difficulty, engagement and age suitability without turning the platform into a permanent learner-surveillance system. | AE14: Implement AN-001 exactly. Do not create a permanent event stream. Maintain one temporary daily buffer row per date-specific HMAC learner key, app and level. Run one idempotent aggregation at 00:15 Asia/Kolkata for the explicit previous date. Create both level and app aggregates; calculate unique active learners independently at each grain. Verify source/control totals before deleting the buffer. On success, delete all target-date daily keys and buffer/contribution receipts. Permanent analytics contains app_id, level, age band and aggregate metrics only—never learner/parent IDs, names, DOB or exact age. Named learner reporting uses only compact current progress and lesson completions. No browser write endpoint, no raw heartbeat rows, no repeated progress snapshots and no named admin drill-down. Exact build packet: CBS-AN-001 | AF14: AT-AN-001-01 through AT-AN-001-35 | AG14: 1.0 | AH14: Product Owner | AI14: 2026-07-30
A15: AR-002 | B15: EP-APPREG-01 | C15: App Registry | D15: Automated Deployment | E15: Automated app deployment, verified release promotion and rollback | F15: Must Have | G15: Approved | H15: Yes | I15: Backlog | J15: Functional | K15: Babysteps Platform | L15: Platform Administrator and Deployment Pipeline | M15: As a platform administrator, I want Babysteps apps to be built, deployed, validated, published and rolled back automatically so learners never depend on manually entered production URLs or unverified releases. | N15: Babysteps shall automate application build, environment deployment, launch-metadata generation, validation, production publication and rollback through a trusted deployment-provider adapter. Administrators bind a registered app to a provider-verified project and approve a release that has already passed staging gates. They never enter or edit a live deployment URL. Each release is an immutable build-once artifact; the same artifact is promoted through staging and production. New learner launches use only the atomically published production deployment, while existing sessions remain bound to the deployment selected at their start. Every production release must be backward compatible with all current platform contracts and every progress schema version present in retained learner progress. Production promotion occurs only inside a pre-scheduled app-specific deployment slot. New learning-session starts are blocked for that app from 60 minutes before the slot until publication or safe rollback completes, and the deployment cannot begin while any starting, active or disconnected/resumable session exists for the app. | O15: 1. Version 1 supports development, staging and production deployment environments. 2. The core deployment service uses a provider-neutral DeploymentProvider interface. The initial implementation is a Vercel adapter. 3. Each app may have at most one verified deployment-project binding per environment. 4. A binding is trusted only after the provider API confirms the project exists, belongs to the approved Babysteps provider team, is accessible to the deployment service account and is connected to the expected repository. 5. The same provider project/environment binding cannot be assigned to two app identities. 6. Administrators select from provider-discovered projects and approved Babysteps domains; they cannot type an arbitrary production URL, provider project ID or unapproved domain and have it trusted. 7. The repository contains a version-controlled babysteps.app.json manifest with manifestVersion, appKey, launchPath, returnPath, identityPath, healthPath and minimum supported platform SDK version. 8. The manifest contains no origin, production URL, SSO secret, API key or credential. 9. Manifest appKey must exactly match the immutable registry app_key. Launch/return/identity/health paths are relative same-origin paths, begin with '/', contain no origin, credentials or fragment and pass strict length/character validation. 10. The platform derives the SSO audience from app_key and environment. The application cannot choose an arbitrary audience. 11. A release is created only by an authenticated CI/deployment service for an approved repository commit. Browser administrators cannot register arbitrary source artifacts. 12. Every release has immutable release_id, source commit SHA, dependency-lock hash, build-input hash and artifact digest. 13. Mutable labels such as latest, main or production are never the authoritative release identity. 14. The pipeline builds the artifact once. Staging and production promotion use the exact same artifact digest; production must not rebuild from source. 15. Required build checks include dependency installation from the lockfile, type checking, linting, unit tests, contract tests, security checks and production build success. 16. A failed mandatory check marks the release failed and prevents staging or production promotion. 17. Development/preview deployments use development credentials only, cannot receive production learner tokens or production learner data and expire automatically. 18. A verified release is deployed to staging automatically after build gates pass, or by an authorized explicit staging action when the pipeline is configured for manual staging. 19. Staging validation checks provider success, approved origin, manifest identity, runtime app_id/app_key identity response, health endpoint, launch handshake, SSO audience, callback/return contract, progress contract, session heartbeat contract, exact CORS/message origins, minimum SDK compatibility and basic accessibility smoke tests. 20. A release reaches verified only when every mandatory staging validation passes. 21. Production promotion requires app_deployment_promote permission, recent administrator reauthentication and explicit approval of a specific immutable release. 22. Approval displays app identity, release ID, commit SHA, artifact digest, staging results, current production release and rollback target. 23. Promotion acquires a per-app production lock and revalidates app active status, pipeline enabled state, binding, immutable artifact digest and all required checks. 24. The provider-confirmed production deployment URL/origin is accepted only from the authenticated provider API or verified signed webhook, normalized and matched to an approved Babysteps domain. 25. Browser/admin payloads cannot provide or override the production launch origin. 26. Production smoke validation runs before the platform publishes the deployment to learner launches. 27. If provider deployment or prepublication validation fails, the current published deployment remains unchanged and the failed release is never exposed to new learners. 28. Publication is an atomic update of current_published_deployment_id and previous_healthy_deployment_id for the app/environment. 29. Only a published production deployment may be resolved by the launch service for a new learner session. 30. Every session launch records deployment_id and release_id in its temporary active-session state. Existing active/resumable sessions continue on their original deployment after a new publication. 31. The immediately previous healthy production deployment is retained as the rollback target. 32. After publication, the pipeline performs a ten-minute release-safety observation with one critical check per minute. One identity/SSO-integrity failure or three consecutive critical availability/contract failures triggers automated rollback. 33. Automated rollback atomically restores the previous healthy deployment for new launches, marks the failed deployment rolled_back and alerts administrators. It does not redirect or mutate existing active sessions. 34. Continuous availability and maintenance behavior after the ten-minute release-safety window belongs to AR-003. 35. An authorized administrator may trigger the same automated rollback manually using a specific current deployment and expected publication version. 36. Concurrent production promotions or rollbacks for the same app are serialized; only one may commit. 37. Provider webhooks require signature verification, timestamp tolerance, event-ID idempotency and replay rejection. 38. Deployment provider credentials and environment secrets are stored only in the secrets manager and are separated by environment. 39. Soft-deleted apps and apps with deployment_enabled=false cannot create, promote, publish or roll back to a new deployment. 40. Detailed build logs, provider webhook payloads, preview deployments and repeated validation responses are temporary and automatically purged under explicit retention rules. 41. Babysteps retains only the current published deployment, previous healthy rollback deployment, current verified release awaiting approval, a failed release linked to an open investigation and compact release/promotion audit metadata. 42. Deployment data contains no learner identity or progress data. 43. Every binding, promotion and rollback mutation uses optimistic versioning and administrator/service-scoped idempotency. 44. No direct repository or application credential may change App Registry or publication pointers. 45. All state changes use transactional outbox/audit events and fail without partial publication. 46. Every release must be backward compatible with the currently published platform/app contracts and every schema version present in retained learner_app_progress rows. 47. Compatibility uses expand/migrate/contract sequencing. A production release must not combine a destructive schema removal with code that still depends on the removed shape. 48. Before verification, the pipeline enumerates persisted progress schema versions and runs read/migrate/write compatibility tests for each represented version. 49. A release may write the new schema version only after it can safely read or migrate every represented prior version. Failed migration or rollback-compatibility testing blocks production. 50. Production promotion requires one pre-scheduled app-specific deployment window with starts_at and ends_at. 51. The deployment window must be scheduled at least 60 minutes before starts_at. drain_starts_at is starts_at minus 60 minutes. 52. From drain_starts_at, LP-004 blocks all new normal and replacement session starts for that app. Other apps remain available. 53. A blocked deployment-drain attempt consumes no weekly slot, replacement credit, learner session or launch code. 54. Existing sessions may complete or use their existing same-device recovery allowance during the drain. 55. At starts_at the deployment service must confirm zero starting, active or disconnected/resumable learner sessions for the app. If any remain, do not deploy; postpone/fail the window and alert administrators. 56. No learner session may start during the scheduled deployment window. 57. Production promotion, validation, publication and any rollback must run within the deployment window when possible. 58. If safe publication or rollback is not complete by ends_at, continue blocking new sessions for that app until the previously published deployment is revalidated or a verified deployment/rollback is atomically published. 59. Deployment-window blocking is a narrow release-control feature owned by AR-002 and does not activate the deferred AR-003 maintenance/availability state machine. 60. A window mutation requires versioning, idempotency, administrator permission, recent reauthentication and an immutable approved release target. | P15: AR-001 app registry; administrator RBAC and reauthentication; approved domain registry; secrets manager; source-control/CI integration; provider service account; BB-04 launch/SSO contracts; LP-004 active-session binding; progress and heartbeat contract test fixtures; audit/outbox and alerting. | Q15: A deployment binding is created or verified, an approved repository commit produces a CI release, a verified release becomes available for staging or an authorized administrator approves production promotion/rollback. | R15: Project binding: 1. Admin opens /admin/apps/{appId}/deployments and selects a provider project discovered under the approved Babysteps team. 2. Server verifies project ownership, repository, environment and approved domain. 3. Binding is stored with version and verified status. Release: 4. CI submits commit SHA, lock hash, build-input hash and idempotency key. 5. Pipeline builds once, calculates artifact digest and runs required checks. 6. Passing artifact is deployed to staging. 7. Platform reads the versioned manifest and validates app identity, routes and integration contracts. 8. Passing release becomes verified and awaits production approval. Production: 9. Reauthenticated authorized admin reviews the immutable release and approves promotion. 10. Server acquires app production lock and revalidates every gate. 11. Provider promotes the same artifact; platform retrieves and verifies the provider-confirmed origin. 12. Production smoke tests pass. 13. Platform atomically publishes the deployment and records the previous healthy deployment. 14. New sessions use the new deployment; existing sessions retain their original deployment. 15. Ten-minute release-safety checks run. 16. A qualifying critical failure automatically restores the previous healthy publication and alerts administrators. Retention: 17. Expired previews, superseded staging deployments, detailed logs and processed webhook payloads are purged. 18. Minimum current/rollback/review metadata remains. Scheduled production window: 19. Admin selects the verified release and schedules an app-specific production slot at least 60 minutes in advance. 20. Platform records drain_starts_at and exposes the block to LP-004. 21. At drain start, new sessions for that app are rejected without usage consumption; existing sessions finish or resume normally. 22. At slot start, the pipeline verifies zero reserved learner sessions for the app. 23. If zero, promotion proceeds using the same artifact. If not, the window is postponed/failed without deployment. 24. Compatibility migrations use expand/migrate/contract and are validated before publication. 25. The app remains start-blocked through production validation and publication/rollback. 26. On safe completion, the block is removed and new sessions may start. | S15: Unknown/soft-deleted app: APP_NOT_ACTIVE. Unsupported provider: DEPLOYMENT_PROVIDER_UNSUPPORTED. Provider unavailable: DEPLOYMENT_PROVIDER_UNAVAILABLE. Project missing/inaccessible/wrong team: DEPLOYMENT_PROJECT_NOT_VERIFIED. Repository mismatch: DEPLOYMENT_REPOSITORY_MISMATCH. Project already bound: DEPLOYMENT_PROJECT_ALREADY_BOUND. Unapproved domain: DEPLOYMENT_DOMAIN_NOT_APPROVED. Invalid/mismatched manifest: APP_MANIFEST_INVALID or APP_IDENTITY_MISMATCH. Invalid relative path: APP_MANIFEST_PATH_INVALID. Duplicate release commit/artifact retry: return original release. Same idempotency key with changed input: IDEMPOTENCY_KEY_REUSED. Build/test/security failure: RELEASE_BUILD_FAILED or RELEASE_GATE_FAILED. Artifact digest changes after verification: RELEASE_ARTIFACT_CHANGED and security alert. Staging deployment/contract failure: STAGING_VALIDATION_FAILED. Release not verified: RELEASE_NOT_VERIFIED. Missing permission/reauth: FORBIDDEN or REAUTHENTICATION_REQUIRED. Pipeline disabled: DEPLOYMENT_PIPELINE_DISABLED. Concurrent promotion: DEPLOYMENT_PROMOTION_IN_PROGRESS. Stale binding/publication version: DEPLOYMENT_VERSION_CONFLICT. Provider URL not authenticated/approved: DEPLOYMENT_ORIGIN_REJECTED. Production smoke failure: PRODUCTION_VALIDATION_FAILED; current publication unchanged. Publication transaction failure: rollback all pointer/event state. Forged/replayed webhook: WEBHOOK_SIGNATURE_INVALID or WEBHOOK_REPLAYED. No previous healthy deployment: ROLLBACK_TARGET_NOT_AVAILABLE. Rollback provider failure: ROLLBACK_FAILED; fail closed, keep last known publication pointer and alert. Soft delete during pipeline: cancel remaining work; never publish. Expired preview access: DEPLOYMENT_EXPIRED. Secrets/log redaction failure: deployment fails security gate. Deployment slot scheduled with less than 60 minutes lead: DEPLOYMENT_WINDOW_LEAD_TIME_REQUIRED. Overlapping deployment slot for same app: DEPLOYMENT_WINDOW_CONFLICT. Session start during drain/window: APP_DEPLOYMENT_WINDOW_BLOCKED; no slot/credit/session consumed. Reserved session remains at slot start: DEPLOYMENT_SESSIONS_ACTIVE; do not deploy. Compatibility matrix or persisted progress migration fails: RELEASE_BACKWARD_COMPATIBILITY_FAILED. Window ends before safe publication: retain start block until previous/current deployment is verified or rollback completes. | T15: Binding: appId, environment, provider and provider-discovered project selection, approvedDomainId, expectedRepository, deploymentEnabled, expectedVersion, idempotencyKey. Release: appId, repository/commit SHA, lock/build hashes and CI attestation. Promotion/rollback: releaseId or deploymentId, expected publication/binding version, idempotencyKey and approval reason. Deployment window: startsAt, endsAt, releaseId, expectedVersion, idempotencyKey and reason. | U15: Verified deployment binding; immutable release and artifact digest; staging/production deployment records; compact validation summary; current/previous publication pointers; generated safe launch configuration; deployment/audit events; automatic rollback result. No administrator-entered live URL. Versioned deployment window, drain state, compatibility report and final unblock/extended-block result. | V15: Admin route: - /admin/apps/{appId}/deployments Binding view: - Provider and environment. - Provider-discovered project picker. - Verified team, repository and approved domain. - Pipeline enabled/disabled state. - No free-text live URL or production-origin input. Release view: - Release ID, source commit, build number, artifact digest and check summary. - Staging deployment and validation status. - Current production and previous rollback release. - Detailed logs linked temporarily only for authorized troubleshooting. Promotion: - Approve production button only for verified immutable release. - Recent reauthentication. - Confirmation page comparing current and proposed release. - Show that the same staging-tested artifact is promoted without rebuild. Rollback: - Roll back to previous healthy release action with reason and confirmation. - Display new-session effect and state that existing sessions remain unchanged. States: queued, building, testing, deploying_staging, staging_validation, verified, awaiting_production_approval, deploying_production, production_validation, published, failed, rolled_back, cancelled, expired. Accessible, responsive at 320px, no secrets or learner data, and clear retry/failure messages. Deployment scheduling: - Verified release has Schedule production deployment. - Choose an app-specific start/end slot at least 60 minutes ahead. - Show automatic drain start, affected app only, current reserved session count and compatibility result. - Explain no new sessions can start during drain/window and blocked attempts use no allowance. - At slot time show waiting-for-zero-sessions, deploying, validating, published, rolled back or extended safe-block state. | W15: GET /v1/admin/apps/{appId}/deployment-bindings POST /v1/admin/apps/{appId}/deployment-bindings PATCH /v1/admin/apps/{appId}/deployment-bindings/{environment} POST /v1/admin/apps/{appId}/deployment-bindings/{environment}/verify GET /v1/admin/apps/{appId}/releases GET /v1/admin/apps/{appId}/deployments POST /v1/admin/apps/{appId}/releases/{releaseId}/deploy-staging POST /v1/admin/apps/{appId}/releases/{releaseId}/approve-production POST /v1/admin/apps/{appId}/deployments/{deploymentId}/rollback POST /v1/internal/apps/{appId}/releases POST /v1/internal/deployment-provider/webhook GET /v1/internal/apps/{appId}/published-deployment?environment=production No endpoint accepts launchOrigin, productionUrl or arbitrary redirect origin from an administrator/browser. Internal launch read returns only an active app's atomically published deployment and generated launch metadata. GET /v1/admin/apps/{appId}/deployment-windows POST /v1/admin/apps/{appId}/deployment-windows PATCH /v1/admin/apps/{appId}/deployment-windows/{windowId} POST /v1/admin/apps/{appId}/deployment-windows/{windowId}/cancel GET /v1/internal/apps/{appId}/deployment-start-block Production approval references an approved deploymentWindowId. No immediate unscheduled production promotion is permitted. | X15: app_deployment_bindings: - id uuid primary key - app_id uuid not null references app_registry(id) on delete restrict - environment text not null check development|staging|production - provider text not null - provider_team_id text not null - provider_project_id text not null - expected_repository text not null - approved_domain_id uuid null - binding_status text not null check unverified|verified|disabled - deployment_enabled boolean not null default true - verified_at timestamptz null - version integer not null default 1 - created_at/updated_at - unique(app_id,environment) - unique(provider,provider_team_id,provider_project_id,environment) app_releases: - id uuid primary key - app_id uuid not null - source_repository text not null - source_commit_sha text not null - dependency_lock_hash text not null - build_input_hash text not null - artifact_digest text not null - provider_artifact_id text null - manifest_json jsonb not null safe non-secret validated projection - status text not null - created_by_ci_principal text not null - created_at/verified_at/failed_at - immutable after creation except status/timestamps - unique(app_id,source_commit_sha,artifact_digest) app_deployments: - id uuid primary key - app_id uuid not null - release_id uuid not null - binding_id uuid not null - environment text not null - provider_deployment_id text not null unique - verified_origin text not null - status text not null - validation_summary jsonb not null safe compact codes/totals only - started_at/validated_at/published_at/superseded_at/ended_at - investigation_hold boolean not null default false - no learner fields app_environment_publications: - app_id uuid not null - environment text not null - current_published_deployment_id uuid null - previous_healthy_deployment_id uuid null - version integer not null default 1 - published_at timestamptz null - primary key(app_id,environment) deployment_operation_requests: - actor_principal_id, app_id, idempotency_key composite unique - operation, request_hash, release/deployment/result IDs, status, timestamps, safe response deployment_webhook_receipts: - provider, provider_event_id unique, received_at, processed_at, status - short retention after processing Use transactional outbox/audit. Detailed provider/build logs stay outside core DB or in short-retention storage. No manual app_environment_config origin table; generated launch metadata is derived from the current published deployment plus the validated manifest and platform environment. app_deployment_windows: - id uuid primary key - app_id uuid not null - release_id uuid not null - starts_at / ends_at timestamptz not null - drain_starts_at generated/validated as starts_at - interval '60 minutes' - status scheduled|draining|executing|completed|cancelled|failed|extended_safe_block - failure_code text null - created_by_admin_id uuid not null - version integer not null default 1 - created_at/updated_at/completed_at - exclusion/transaction rule preventing overlapping non-final windows per app - short operational retention after compact audit and incident closure app_release_compatibility_reports: - release_id primary key - platform_contract_version - represented_progress_schema_versions jsonb - migration/rollback test result codes - status passed|failed - generated_at - compact report retained while release is current/rollback/review target. | Y15: Provider credentials and environment secrets are secrets-manager references only and are never stored in registry/deployment rows or returned to browsers. Separate development, staging and production principals and secret scopes. Provider API/webhooks require TLS, signature verification, replay protection and allowlisted provider endpoints. Repository and commit are validated against approved binding and CI attestation. Artifact digest is checked before every promotion; build once and never rebuild during promotion. Production approval and rollback require granular permission, recent reauthentication and explicit immutable target. Approved domain registry and provider ownership checks prevent arbitrary redirect origins. Generated SSO audience and launch metadata are server authoritative. Preview/staging deployments cannot receive production learner token audience or production data access. Soft-deleted/disabled app fails closed. Release/build logs redact credentials, tokens, learner data and environment secrets. Audit records IDs, commit/digest, operation, actor, result and reason without retaining full logs. No repository workflow or app code may mutate publication pointers directly. Deployment-window scheduling/cancellation requires granular permission and recent reauthentication. The start-block is server-authoritative and cannot be bypassed by an app or browser. | Z15: Build/promotion operations are asynchronous and expose status; admin HTTP commands acknowledge within 2 seconds. Provider webhook processing is idempotent. At most one production promotion/rollback per app executes. Publication pointer update and outbox are atomic. New launch resolution p95 under 500 ms from cached publication state. Build once/artifact digest equality is contract tested. Prepublication failure exposes zero new learner launches. Automatic rollback completes within five minutes of a qualifying release-safety trigger when provider service is available. Ten-minute release-safety observation is restart safe. Existing sessions remain deployment-stable. Preview/log/webhook cleanup is automatic and measurable. Core database retains only minimal current/rollback/review deployment metadata. Provider adapter has contract tests independent of Vercel implementation. Admin UI is accessible and responsive at 320px. Deployment drain becomes visible to the session-start transaction within 5 seconds. Compatibility tests cover every represented progress schema. Window execution is restart-safe and app-specific. | AA15: AC1 Provider-neutral deployment interface exists with a Vercel Version 1 adapter. AC2 Admin binds an app/environment only to a provider-discovered verified project. AC3 Wrong team, inaccessible project or repository mismatch is rejected. AC4 One provider project/environment cannot represent two apps. AC5 Admin UI/API has no free-text production URL or launch-origin mutation. AC6 Versioned manifest contains valid app key and relative paths only. AC7 Manifest app key mismatch blocks release. AC8 CI alone creates release from approved commit. AC9 Release commit, lock hash, build-input hash and artifact digest are immutable. AC10 Pipeline builds artifact once. AC11 Staging and production use the identical artifact digest. AC12 Mandatory build/test/security failure prevents deployment. AC13 Development preview has no production token/data access and expires. AC14 Staging deployment runs all required identity/launch/progress/session/SDK/accessibility checks. AC15 Any mandatory staging failure prevents verified status. AC16 Verified release is displayed with commit/digest/check summary. AC17 Production promotion requires permission, recent reauth and explicit immutable release approval. AC18 Soft-deleted or pipeline-disabled app cannot promote. AC19 Concurrent promotions serialize and only one commits. AC20 Provider-confirmed origin must use approved Babysteps domain. AC21 Browser/admin cannot override provider origin. AC22 Production smoke failure leaves current publication unchanged. AC23 Successful publication atomically sets current and previous deployment pointers. AC24 New sessions use only current published deployment. AC25 Existing sessions retain original deployment after publication. AC26 Previous healthy deployment remains available for rollback. AC27 Qualifying ten-minute safety-window failure triggers automated rollback. AC28 Manual rollback uses the same automated path and requires permission/reauth. AC29 Rollback changes new launches but not existing sessions. AC30 Forged/replayed provider webhook is rejected. AC31 Duplicate webhook/operation does not duplicate deployment or publication. AC32 Secrets and learner data are absent from deployment rows, logs and UI. AC33 Old previews, superseded staging records and detailed logs are purged. AC34 Minimal current/previous/verified/investigated records remain. AC35 Provider adapter, rollback failure and transaction fault tests pass without partial publication. AC36 Every production release passes backward-compatibility checks for platform contracts and represented progress schemas. AC37 Destructive migration/removal cannot publish in the same incompatible step. AC38 Production promotion requires a deployment window scheduled at least 60 minutes in advance. AC39 New session starts for the app are blocked from drain start through safe completion and consume no allowance. AC40 Other apps remain available during the window. AC41 Deployment does not begin while any reserved learner session for the app exists. AC42 Window overrun remains fail-closed until safe current deployment or rollback is verified. | AB15: AR-001; BB-04 app launch and SSO; LP-004 deployment-bound active session; AR-003 ongoing availability/maintenance; admin RBAC; approved domain registry; CI/source control; secrets manager; audit/outbox; alerting; BB-18 broader deployment recovery policy. | AC15: Automated, immutable release promotion protects learner continuity while keeping app identity and learner progress independent from changing infrastructure. | AE15: Implement AR-002 exactly. OBJECTIVE Automate Babysteps app build, deployment, validation, publication and rollback. Administrators approve verified immutable releases; they never type production URLs. PROVIDER Create a DeploymentProvider interface and Vercel adapter. Verify provider team, project, repository and approved domain. One verified binding per app/environment; no cross-app reuse. MANIFEST Require version-controlled babysteps.app.json with appKey and relative launch/return/identity/health paths plus minimum SDK version. No origin, audience or secret. Match appKey to AR-001. Derive SSO audience server-side. RELEASE CI service alone creates immutable release from approved commit. Record commit SHA, lock hash, build-input hash and artifact digest. Build once. Promote the identical artifact digest to staging and production—never rebuild at promotion. GATES Run type/lint/unit/contract/security/build gates. Deploy passing artifact to staging and validate provider status, approved origin, identity endpoint, manifest, launch/SSO/callback, progress, session heartbeat, CORS/message origins, SDK and accessibility smoke. Only all-pass release becomes verified. PRODUCTION Require app_deployment_promote permission, recent reauth and explicit verified release approval. Acquire per-app lock; revalidate app/binding/release/digest. Provider promotes same artifact and returns origin. Reject browser/admin origin values. Verify approved domain and production smoke before publishing. Atomically update current_published_deployment_id and previous_healthy_deployment_id with outbox. New sessions use current; existing sessions keep launch deployment. ROLLBACK Retain previous healthy deployment. Run 10-minute safety observation every minute. One identity/SSO integrity failure or three consecutive critical failures triggers automated rollback. Manual rollback uses the same service and requires permission/reauth. Rollback affects new launches only. Version 1 continuous monitoring beyond the ten-minute release-safety window remains deferred under AR-003. SECURITY Separate environment credentials/secrets in secrets manager. Signed idempotent provider webhooks. No production data/tokens in previews. Soft-deleted/disabled apps cannot deploy. No app/repository may mutate publication pointers. Redact secrets and learner data. DATA/RETENTION Create bindings, immutable releases, deployments, environment publications, operation requests and short-retention webhook receipts exactly as specified. Generated launch metadata comes from current published deployment + validated manifest. Purge old previews, superseded staging, detailed logs and processed webhooks. Retain only current production, previous healthy rollback, verified awaiting approval, failed under investigation and compact audit. TESTS Implement AT-AR-002-01 through AT-AR-002-42. DEFINITION OF DONE No manual production URL surface exists; build-once promotion works; staging gates protect production; publication is atomic; existing sessions remain stable; rollback is automated; retention is minimal; all tests pass. Exact build packet: CBS-AR-002 AMENDMENT — BACKWARD COMPATIBILITY AND DEPLOYMENT WINDOWS - Require backward compatibility with current platform contracts and every progress schema represented in retained learner_app_progress. - Use expand/migrate/contract. Block destructive same-step schema changes. - Add app_deployment_windows and compact compatibility reports. - Production promotion requires a window scheduled >=60 minutes ahead. - Block new starts for that app from starts_at-60m through safe publish/rollback; no slot, credit, session or launch code is consumed. - At slot start require zero starting/active/disconnected sessions for the app; otherwise do not deploy. - Other apps remain available. - Overrun stays fail-closed until old/current deployment is verified or rollback completes. - Add AT-AR-002-36 through AT-AR-002-42. | AF15: AT-AR-002-01 through AT-AR-002-42 | AG15: 1.0 | AH15: Product Owner | AI15: 2026-07-30
A16: AR-003 | B16: EP-APPREG-01 | C16: Deferred App Operations | D16: Availability, Maintenance & Retirement | E16: App availability, maintenance and retirement controls | F16: Should Have | G16: Deferred | H16: No | I16: Deferred | J16: Functional | K16: Babysteps Platform | L16: Platform Administrator and Availability Monitor | M16: As a platform operator, I may later need continuous app-health monitoring, maintenance windows, emergency launch blocking and planned retirement orchestration without changing permanent app identity. | N16: Deferred outside the Version 1 baseline. Version 1 includes AR-002 deployment-time validation, a ten-minute post-publication safety window, automated rollback and administrator-triggered rollback. It does not implement continuous health monitoring, scheduled maintenance/drain states, emergency availability blocks, automatic health recovery or coordinated retirement workflows. | O16: 1. Do not implement continuous per-app health polling in Version 1. 2. Do not create app_availability_state, app_health_state, app_maintenance_windows or app_retirement_plans tables. 3. Do not implement available, degraded, draining, maintenance, unavailable or retirement state machines beyond AR-001 registry status and AR-002 deployment status. 4. Do not add scheduled maintenance, maintenance countdown, emergency block or restore controls to the Version 1 admin interface. 5. Do not implement automatic launch blocking based on continuous synthetic health checks. 6. Do not implement automatic recovery after health-check success. 7. Do not implement a retirement scheduler or billing/communication readiness orchestration. 8. AR-001 soft deletion remains the only app-removal action. 9. AR-002 continues to provide build-time gates, staging validation, production smoke checks, the ten-minute release-safety observation and automated/manual rollback. 10. Existing LP-004 session continuity rules remain unchanged. 11. Version 1 may show normal launch/provider errors when an app cannot be reached; no advanced maintenance-state message contract is required. 12. The future requirement remains visible because safe implementation will require availability thresholds, monitoring-failure policy, launch-slot protection, maintenance drainage, parent communication and commercial retirement coordination. | P16: No implementation prerequisite because the requirement is deferred. | Q16: Future reconsideration after Version 1 operational usage demonstrates a need for continuous availability automation or planned app retirement. | R16: No Version 1 availability-management flow. Do not display Schedule maintenance, Emergency block, Restore availability, Schedule retirement or equivalent controls. | S16: If an unimplemented availability/maintenance/retirement route is requested, return a normal unsupported/not-found response without changing app, deployment, session, billing or entitlement state. | T16: None in Version 1 beyond existing AR-001, AR-002 and LP-004 behavior. | U16: None in Version 1. | V16: No maintenance calendar, health dashboard, emergency availability toggle, retirement wizard or learner maintenance countdown. | W16: No continuous-health, maintenance-window, emergency-block, availability-restore or retirement APIs. | X16: Do not create availability, health-probe-history, maintenance-window or retirement-plan tables, columns, queues or schedulers. | Y16: Version 1 authorization remains limited to AR-001 registry operations and AR-002 deployment promotion/rollback. Do not create availability permissions or let a new route override active learner sessions. | Z16: No Version 1 continuous-health availability target exists. AR-002 release validation and rollback requirements remain authoritative. Architecture scans must confirm that the deferred surface is absent. | AA16: AC1 No continuous app-health monitor exists. AC2 No maintenance scheduling UI/API exists. AC3 No emergency availability block exists. AC4 No automatic health recovery exists. AC5 No retirement workflow exists. AC6 AR-001 soft deletion remains the only app-removal action. AC7 AR-002 deployment validation and rollback remain intact. AC8 Deferred scope is excluded from Version 1 counts. | AB16: Future monitoring thresholds, maintenance drainage, outage messaging, launch-slot protection, billing coordination, parent communication and operational-support decisions. | AC16: Deferred because Version 1 can launch safely through AR-002 validation and rollback, while a full availability state machine adds monitoring, communication and commercial coordination that is not currently critical. | AE16: Do not implement AR-003 in Version 1. Keep AR-001 app identity/soft deletion and AR-002 automated deployment/rollback only. Do not create continuous health monitoring, maintenance windows, emergency availability controls, automatic recovery or retirement orchestration. | AF16: No Version 1 acceptance-test suite; deferred-scope architecture scans may verify absence. | AG16: 0.1-deferred | AH16: Product Owner | AI16: 2026-07-30
